{
  "pageSize": [100],
  "page": [56],
  "totalItems": [14659],
  "totalPages": [147],
  "sortBy": ["Licence ID"],
  "sortOrder": ["desc"],
  "items": [
    {
      "licenceID": [241144],
      "licenceNumber": [297244],
      "licensee": ["TWO DEGREES NETWORKS LIMITED"],
      "channel": {},
      "frequency": [939.9],
      "location": ["(TNK-033-038-A)[VCRD]_S_CARRINGTON ROAD PA"],
      "gridRefDefault": ["LAT_LONG_NZGD2000_D2000"],
      "gridReference": ["-38.9442850 174.3182363"],
      "licenceType": ["Other (Spectrum)"],
      "status": ["Current"],
      "txrx": ["RX"],
      "suppressed": [false]
    },
    {
      "licenceID": [241144],
      "licenceNumber": [297244],
      "licensee": ["TWO DEGREES NETWORKS LIMITED"],
      "channel": {},
      "frequency": [939.9],
      "location": ["(TNK-033-038-A)[VCRD]_S_CARRINGTON ROAD"],
      "gridRefDefault": ["LAT_LONG_NZGD2000_D2000"],
      "gridReference": ["-39.2179830 173.9758301"],
      "licenceType": ["Other (Spectrum)"],
      "status": ["Current"],
      "txrx": ["TX"],
      "suppressed": [false]
    },
    {
      "licenceID": [241143],
      "licenceNumber": [297259],
      "licensee": ["TWO DEGREES NETWORKS LIMITED"],
      "channel": {},
      "frequency": [939.9],
      "location": ["(TNK-035-018-A)[VNMB]_S_NORMANBY PA"],
      "gridRefDefault": ["LAT_LONG_NZGD2000_D2000"],
      "gridReference": ["-39.2540838 174.6097865"],
      "licenceType": ["Other (Spectrum)"],
      "status": ["Current"],
      "txrx": ["RX"],
      "suppressed": [false]
    },
    {
      "licenceID": [241143],
      "licenceNumber": [297259],
      "licensee": ["TWO DEGREES NETWORKS LIMITED"],
      "channel": {},
      "frequency": [939.9],
      "location": ["(TNK-035-018-A)[VNMB]_S_NORMANBY"],
      "gridRefDefault": ["LAT_LONG_NZGD2000_D2000"],
      "gridReference": ["-39.5286239 174.2670636"],
      "licenceType": ["Other (Spectrum)"],
      "status": ["Current"],
      "txrx": ["TX"],
      "suppressed": [false]
    },
    {
      "licenceID": [241142],
      "licenceNumber": [297257],
      "licensee": ["TWO DEGREES NETWORKS LIMITED"],
      "channel": {},
      "frequency": [939.9],
      "location": ["(WLG-048-018-A)[VOTH]_S_OTAHOUA (BCL) PA"],
      "gridRefDefault": ["LAT_LONG_NZGD2000_D2000"],
      "gridReference": ["-40.6966830 176.0981111"],
      "licenceType": ["Other (Spectrum)"],
      "status": ["Current"],
      "txrx": ["RX"],
      "suppressed": [false]
    },
    {
      "licenceID": [241142],
      "licenceNumber": [297257],
      "licensee": ["TWO DEGREES NETWORKS LIMITED"],
      "channel": {},
      "frequency": [939.9],
      "location": ["(WLG-048-018-A)[VOTH]_S_OTAHOUA (BCL)"],
      "gridRefDefault": ["LAT_LONG_NZGD2000_D2000"],
      "gridReference": ["-40.9756055 175.7546162"],
      "licenceType": ["Other (Spectrum)"],
      "status": ["Current"],
      "txrx": ["TX"],
      "suppressed": [false]
    },
    {
      "licenceID": [241141],
      "licenceNumber": [297258],
      "licensee": ["TWO DEGREES NETWORKS LIMITED"],
      "channel": {},
      "frequency": [939.9],
      "location": ["(TNK-035-020-A)[VWEG]_S_WEST EGMONT PA"],
      "gridRefDefault": ["LAT_LONG_NZGD2000_D2000"],
      "gridReference": ["-39.0339435 174.2793716"],
      "licenceType": ["Other (Spectrum)"],
      "status": ["Current"],
      "txrx": ["RX"],
      "suppressed": [false]
    },
    {
      "licenceID": [241141],
      "licenceNumber": [297258],
      "licensee": ["TWO DEGREES NETWORKS LIMITED"],
      "channel": {},
      "frequency": [939.9],
      "location": ["(TNK-035-020-A)[VWEG]_S_WEST EGMONT"],
      "gridRefDefault": ["LAT_LONG_NZGD2000_D2000"],
      "gridReference": ["-39.3075299 173.9363912"],
      "licenceType": ["Other (Spectrum)"],
      "status": ["Current"],
      "txrx": ["TX"],
      "suppressed": [false]
    },
    {
      "licenceID": [241140],
      "licenceNumber": [297307],
      "licensee": ["TWO DEGREES NETWORKS LIMITED"],
      "channel": {},
      "frequency": [939.9],
      "location": ["(TNK-035-015-A)[VPTA]_S_PATEA PA"],
      "gridRefDefault": ["LAT_LONG_NZGD2000_D2000"],
      "gridReference": ["-39.3532993 174.8630498"],
      "licenceType": ["Other (Spectrum)"],
      "status": ["Current"],
      "txrx": ["RX"],
      "suppressed": [false]
    },
    {
      "licenceID": [241140],
      "licenceNumber": [297307],
      "licensee": ["TWO DEGREES NETWORKS LIMITED"],
      "channel": {},
      "frequency": [939.9],
      "location": ["(TNK-035-015-A)[VPTA]_S_PATEA"],
      "gridRefDefault": ["LAT_LONG_NZGD2000_D2000"],
      "gridReference": ["-39.6285766 174.5208785"],
      "licenceType": ["Other (Spectrum)"],
      "status": ["Current"],
      "txrx": ["TX"],
      "suppressed": [false]
    },
    {
      "licenceID": [241139],
      "licenceNumber": [297246],
      "licensee": ["TWO DEGREES NETWORKS LIMITED"],
      "channel": {},
      "frequency": [939.9],
      "location": ["(STH-073-055-A)[VMPS]_S_MT PROSPECT TE ANAU PA"],
      "gridRefDefault": ["LAT_LONG_NZGD2000_D2000"],
      "gridReference": ["-45.1597988 168.3539062"],
      "licenceType": ["Other (Spectrum)"],
      "status": ["Current"],
      "txrx": ["RX"],
      "suppressed": [false]
    },
    {
      "licenceID": [241139],
      "licenceNumber": [297246],
      "licensee": ["TWO DEGREES NETWORKS LIMITED"],
      "channel": {},
      "frequency": [939.9],
      "location": ["(STH-073-055-A)[VMPS]_S_MT PROSPECT TE ANAU"],
      "gridRefDefault": ["LAT_LONG_NZGD2000_D2000"],
      "gridReference": ["-45.4126591 167.9497517"],
      "licenceType": ["Other (Spectrum)"],
      "status": ["Current"],
      "txrx": ["TX"],
      "suppressed": [false]
    },
    {
      "licenceID": [241138],
      "licenceNumber": [297321],
      "licensee": ["TWO DEGREES NETWORKS LIMITED"],
      "channel": {},
      "frequency": [939.9],
      "location": ["(STH-073-057-A)[VOUU]_S_OTAUTAU PA"],
      "gridRefDefault": ["LAT_LONG_NZGD2000_D2000"],
      "gridReference": ["-45.8911796 168.4080638"],
      "licenceType": ["Other (Spectrum)"],
      "status": ["Current"],
      "txrx": ["RX"],
      "suppressed": [false]
    },
    {
      "licenceID": [241138],
      "licenceNumber": [297321],
      "licensee": ["TWO DEGREES NETWORKS LIMITED"],
      "channel": {},
      "frequency": [939.9],
      "location": ["(STH-073-057-A)[VOUU]_S_OTAUTAU"],
      "gridRefDefault": ["LAT_LONG_NZGD2000_D2000"],
      "gridReference": ["-46.1439999 167.9985399"],
      "licenceType": ["Other (Spectrum)"],
      "status": ["Current"],
      "txrx": ["TX"],
      "suppressed": [false]
    },
    {
      "licenceID": [241137],
      "licenceNumber": [297302],
      "licensee": ["TWO DEGREES NETWORKS LIMITED"],
      "channel": {},
      "frequency": [939.9],
      "location": ["(OTG-070-028-A)[VATN]_S_ALBERT TOWN NORTH PA"],
      "gridRefDefault": ["LAT_LONG_NZGD2000_D2000"],
      "gridReference": ["-44.3979996 169.6043659"],
      "licenceType": ["Other (Spectrum)"],
      "status": ["Current"],
      "txrx": ["RX"],
      "suppressed": [false]
    },
    {
      "licenceID": [241137],
      "licenceNumber": [297302],
      "licensee": ["TWO DEGREES NETWORKS LIMITED"],
      "channel": {},
      "frequency": [939.9],
      "location": ["(OTG-070-028-A)[VATN]_S_ALBERT TOWN NORTH"],
      "gridRefDefault": ["LAT_LONG_NZGD2000_D2000"],
      "gridReference": ["-44.6556797 169.2109770"],
      "licenceType": ["Other (Spectrum)"],
      "status": ["Current"],
      "txrx": ["TX"],
      "suppressed": [false]
    },
    {
      "licenceID": [241136],
      "licenceNumber": [297243],
      "licensee": ["TWO DEGREES NETWORKS LIMITED"],
      "channel": {},
      "frequency": [939.9],
      "location": ["(STH-073-049-A)[VCEN]_S_CENTRE HILL PA"],
      "gridRefDefault": ["LAT_LONG_NZGD2000_D2000"],
      "gridReference": ["-45.3282245 168.4963650"],
      "licenceType": ["Other (Spectrum)"],
      "status": ["Current"],
      "txrx": ["RX"],
      "suppressed": [false]
    },
    {
      "licenceID": [241136],
      "licenceNumber": [297243],
      "licensee": ["TWO DEGREES NETWORKS LIMITED"],
      "channel": {},
      "frequency": [939.9],
      "location": ["(STH-073-049-A)[VCEN]_S_CENTRE HILL"],
      "gridRefDefault": ["LAT_LONG_NZGD2000_D2000"],
      "gridReference": ["-45.5815582 168.0915383"],
      "licenceType": ["Other (Spectrum)"],
      "status": ["Current"],
      "txrx": ["TX"],
      "suppressed": [false]
    },
    {
      "licenceID": [241135],
      "licenceNumber": [297293],
      "licensee": ["TWO DEGREES NETWORKS LIMITED"],
      "channel": {},
      "frequency": [939.9],
      "location": ["(AKL-007-284-A)[VCLR]_S_CLARIS PA"],
      "gridRefDefault": ["LAT_LONG_NZGD2000_D2000"],
      "gridReference": ["-35.9768344 175.7679165"],
      "licenceType": ["Other (Spectrum)"],
      "status": ["Current"],
      "txrx": ["RX"],
      "suppressed": [false]
    },
    {
      "licenceID": [241135],
      "licenceNumber": [297293],
      "licensee": ["TWO DEGREES NETWORKS LIMITED"],
      "channel": {},
      "frequency": [939.9],
      "location": ["(AKL-007-284-A)[VCLR]_S_CLARIS"],
      "gridRefDefault": ["LAT_LONG_NZGD2000_D2000"],
      "gridReference": ["-36.2542752 175.4438425"],
      "licenceType": ["Other (Spectrum)"],
      "status": ["Current"],
      "txrx": ["TX"],
      "suppressed": [false]
    },
    {
      "licenceID": [241134],
      "licenceNumber": [297317],
      "licensee": ["TWO DEGREES NETWORKS LIMITED"],
      "channel": {},
      "frequency": [939.9],
      "location": ["(OTG-070-030-A)[VGBY]_S_GLENDHU BAY PA"],
      "gridRefDefault": ["LAT_LONG_NZGD2000_D2000"],
      "gridReference": ["-44.4116587 169.4290099"],
      "licenceType": ["Other (Spectrum)"],
      "status": ["Current"],
      "txrx": ["RX"],
      "suppressed": [false]
    },
    {
      "licenceID": [241134],
      "licenceNumber": [297317],
      "licensee": ["TWO DEGREES NETWORKS LIMITED"],
      "channel": {},
      "frequency": [939.9],
      "location": ["(OTG-070-030-A)[VGBY]_S_GLENDHU BAY"],
      "gridRefDefault": ["LAT_LONG_NZGD2000_D2000"],
      "gridReference": ["-44.6687065 169.0347856"],
      "licenceType": ["Other (Spectrum)"],
      "status": ["Current"],
      "txrx": ["TX"],
      "suppressed": [false]
    },
    {
      "licenceID": [241133],
      "licenceNumber": [297327],
      "licensee": ["TWO DEGREES NETWORKS LIMITED"],
      "channel": {},
      "frequency": [939.9],
      "location": ["(OTG-069-009-A)[VOSK]_S_OBELISK (BCL) PA"],
      "gridRefDefault": ["LAT_LONG_NZGD2000_D2000"],
      "gridReference": ["-45.0644187 169.6051366"],
      "licenceType": ["Other (Spectrum)"],
      "status": ["Current"],
      "txrx": ["RX"],
      "suppressed": [false]
    },
    {
      "licenceID": [241133],
      "licenceNumber": [297327],
      "licensee": ["TWO DEGREES NETWORKS LIMITED"],
      "channel": {},
      "frequency": [939.9],
      "location": ["(OTG-069-009-A)[VOSK]_S_OBELISK (BCL)"],
      "gridRefDefault": ["LAT_LONG_NZGD2000_D2000"],
      "gridReference": ["-45.3219218 169.2069825"],
      "licenceType": ["Other (Spectrum)"],
      "status": ["Current"],
      "txrx": ["TX"],
      "suppressed": [false]
    },
    {
      "licenceID": [241132],
      "licenceNumber": [297331],
      "licensee": ["TWO DEGREES NETWORKS LIMITED"],
      "channel": {},
      "frequency": [939.9],
      "location": ["(OTG-069-020-A)[VMFT]_S_MILLERS FLAT PA"],
      "gridRefDefault": ["LAT_LONG_NZGD2000_D2000"],
      "gridReference": ["-45.4188330 169.8480074"],
      "licenceType": ["Other (Spectrum)"],
      "status": ["Current"],
      "txrx": ["RX"],
      "suppressed": [false]
    },
    {
      "licenceID": [241132],
      "licenceNumber": [297331],
      "licensee": ["TWO DEGREES NETWORKS LIMITED"],
      "channel": {},
      "frequency": [939.9],
      "location": ["(OTG-069-020-A)[VMFT]_S_MILLERS FLAT"],
      "gridRefDefault": ["LAT_LONG_NZGD2000_D2000"],
      "gridReference": ["-45.6771320 169.4483070"],
      "licenceType": ["Other (Spectrum)"],
      "status": ["Current"],
      "txrx": ["TX"],
      "suppressed": [false]
    },
    {
      "licenceID": [241131],
      "licenceNumber": [297236],
      "licensee": ["TWO DEGREES NETWORKS LIMITED"],
      "channel": {},
      "frequency": [939.9],
      "location": ["(AKL-007-285-A)[VGBI]_S_GREAT BARRIER ISLAND PA"],
      "gridRefDefault": ["LAT_LONG_NZGD2000_D2000"],
      "gridReference": ["-35.9057875 175.6517527"],
      "licenceType": ["Other (Spectrum)"],
      "status": ["Current"],
      "txrx": ["RX"],
      "suppressed": [false]
    },
    {
      "licenceID": [241131],
      "licenceNumber": [297236],
      "licensee": ["TWO DEGREES NETWORKS LIMITED"],
      "channel": {},
      "frequency": [939.9],
      "location": ["(AKL-007-285-A)[VGBI]_S_GREAT BARRIER ISLAND"],
      "gridRefDefault": ["LAT_LONG_NZGD2000_D2000"],
      "gridReference": ["-36.1829225 175.3275346"],
      "licenceType": ["Other (Spectrum)"],
      "status": ["Current"],
      "txrx": ["TX"],
      "suppressed": [false]
    },
    {
      "licenceID": [241130],
      "licenceNumber": [297269],
      "licensee": ["TWO DEGREES NETWORKS LIMITED"],
      "channel": {},
      "frequency": [939.9],
      "location": ["(OTG-070-031-A)[VGNC]_S_GLENORCHY CENTRAL PA"],
      "gridRefDefault": ["LAT_LONG_NZGD2000_D2000"],
      "gridReference": ["-44.6147335 168.7457729"],
      "licenceType": ["Other (Spectrum)"],
      "status": ["Current"],
      "txrx": ["RX"],
      "suppressed": [false]
    },
    {
      "licenceID": [241130],
      "licenceNumber": [297269],
      "licensee": ["TWO DEGREES NETWORKS LIMITED"],
      "channel": {},
      "frequency": [939.9],
      "location": ["(OTG-070-031-A)[VGNC]_S_GLENORCHY CENTRAL"],
      "gridRefDefault": ["LAT_LONG_NZGD2000_D2000"],
      "gridReference": ["-44.8692212 168.3472649"],
      "licenceType": ["Other (Spectrum)"],
      "status": ["Current"],
      "txrx": ["TX"],
      "suppressed": [false]
    },
    {
      "licenceID": [241129],
      "licenceNumber": [297326],
      "licensee": ["TWO DEGREES NETWORKS LIMITED"],
      "channel": {},
      "frequency": [939.9],
      "location": ["(STH-073-051-A)[VGSN]_S_GARSTON PA"],
      "gridRefDefault": ["LAT_LONG_NZGD2000_D2000"],
      "gridReference": ["-45.1222564 169.1091357"],
      "licenceType": ["Other (Spectrum)"],
      "status": ["Current"],
      "txrx": ["RX"],
      "suppressed": [false]
    },
    {
      "licenceID": [241129],
      "licenceNumber": [297326],
      "licensee": ["TWO DEGREES NETWORKS LIMITED"],
      "channel": {},
      "frequency": [939.9],
      "location": ["(STH-073-051-A)[VGSN]_S_GARSTON"],
      "gridRefDefault": ["LAT_LONG_NZGD2000_D2000"],
      "gridReference": ["-45.3779325 168.7084367"],
      "licenceType": ["Other (Spectrum)"],
      "status": ["Current"],
      "txrx": ["TX"],
      "suppressed": [false]
    },
    {
      "licenceID": [241128],
      "licenceNumber": [297312],
      "licensee": ["TWO DEGREES NETWORKS LIMITED"],
      "channel": {},
      "frequency": [939.9],
      "location": ["(OTG-072-017-A)[VCLN]_S_CLINTON PA"],
      "gridRefDefault": ["LAT_LONG_NZGD2000_D2000"],
      "gridReference": ["-45.9793565 169.7759644"],
      "licenceType": ["Other (Spectrum)"],
      "status": ["Current"],
      "txrx": ["RX"],
      "suppressed": [false]
    },
    {
      "licenceID": [241128],
      "licenceNumber": [297312],
      "licensee": ["TWO DEGREES NETWORKS LIMITED"],
      "channel": {},
      "frequency": [939.9],
      "location": ["(OTG-072-017-A)[VCLN]_S_CLINTON"],
      "gridRefDefault": ["LAT_LONG_NZGD2000_D2000"],
      "gridReference": ["-46.2372539 169.3717409"],
      "licenceType": ["Other (Spectrum)"],
      "status": ["Current"],
      "txrx": ["TX"],
      "suppressed": [false]
    },
    {
      "licenceID": [241127],
      "licenceNumber": [297233],
      "licensee": ["TWO DEGREES NETWORKS LIMITED"],
      "channel": {},
      "frequency": [939.9],
      "location": ["(STH-073-053-A)[VMDD]_S_MID DOME PA"],
      "gridRefDefault": ["LAT_LONG_NZGD2000_D2000"],
      "gridReference": ["-45.3297775 168.9398770"],
      "licenceType": ["Other (Spectrum)"],
      "status": ["Current"],
      "txrx": ["RX"],
      "suppressed": [false]
    },
    {
      "licenceID": [241127],
      "licenceNumber": [297233],
      "licensee": ["TWO DEGREES NETWORKS LIMITED"],
      "channel": {},
      "frequency": [939.9],
      "location": ["(STH-073-053-A)[VMDD]_S_MID DOME"],
      "gridRefDefault": ["LAT_LONG_NZGD2000_D2000"],
      "gridReference": ["-45.5847656 168.5369122"],
      "licenceType": ["Other (Spectrum)"],
      "status": ["Current"],
      "txrx": ["TX"],
      "suppressed": [false]
    },
    {
      "licenceID": [241126],
      "licenceNumber": [297278],
      "licensee": ["TWO DEGREES NETWORKS LIMITED"],
      "channel": {},
      "frequency": [939.9],
      "location": ["(OTG-071-060-A)[VMDM]_S_MIDDLEMARCH PA"],
      "gridRefDefault": ["LAT_LONG_NZGD2000_D2000"],
      "gridReference": ["-45.2887376 170.4398167"],
      "licenceType": ["Other (Spectrum)"],
      "status": ["Current"],
      "txrx": ["RX"],
      "suppressed": [false]
    },
    {
      "licenceID": [241126],
      "licenceNumber": [297278],
      "licensee": ["TWO DEGREES NETWORKS LIMITED"],
      "channel": {},
      "frequency": [939.9],
      "location": ["(OTG-071-060-A)[VMDM]_S_MIDDLEMARCH"],
      "gridRefDefault": ["LAT_LONG_NZGD2000_D2000"],
      "gridReference": ["-45.5492078 170.0436711"],
      "licenceType": ["Other (Spectrum)"],
      "status": ["Current"],
      "txrx": ["TX"],
      "suppressed": [false]
    },
    {
      "licenceID": [241125],
      "licenceNumber": [297242],
      "licensee": ["TWO DEGREES NETWORKS LIMITED"],
      "channel": {},
      "frequency": [939.9],
      "location": ["(OTG-070-033-A)[VWWN]_S_WEST WANAKA PA"],
      "gridRefDefault": ["LAT_LONG_NZGD2000_D2000"],
      "gridReference": ["-44.4299802 169.4779961"],
      "licenceType": ["Other (Spectrum)"],
      "status": ["Current"],
      "txrx": ["RX"],
      "suppressed": [false]
    },
    {
      "licenceID": [241125],
      "licenceNumber": [297242],
      "licensee": ["TWO DEGREES NETWORKS LIMITED"],
      "channel": {},
      "frequency": [939.9],
      "location": ["(OTG-070-033-A)[VWWN]_S_WEST WANAKA"],
      "gridRefDefault": ["LAT_LONG_NZGD2000_D2000"],
      "gridReference": ["-44.6872015 169.0838560"],
      "licenceType": ["Other (Spectrum)"],
      "status": ["Current"],
      "txrx": ["TX"],
      "suppressed": [false]
    },
    {
      "licenceID": [241124],
      "licenceNumber": [297252],
      "licensee": ["TWO DEGREES NETWORKS LIMITED"],
      "channel": {},
      "frequency": [939.9],
      "location": ["(MNW-036-023-A)[VOHR]_S_OHURA PA"],
      "gridRefDefault": ["LAT_LONG_NZGD2000_D2000"],
      "gridReference": ["-38.5751453 175.2751080"],
      "licenceType": ["Other (Spectrum)"],
      "status": ["Current"],
      "txrx": ["RX"],
      "suppressed": [false]
    },
    {
      "licenceID": [241124],
      "licenceNumber": [297252],
      "licensee": ["TWO DEGREES NETWORKS LIMITED"],
      "channel": {},
      "frequency": [939.9],
      "location": ["(MNW-036-023-A)[VOHR]_S_OHURA"],
      "gridRefDefault": ["LAT_LONG_NZGD2000_D2000"],
      "gridReference": ["-38.8515293 174.9382081"],
      "licenceType": ["Other (Spectrum)"],
      "status": ["Current"],
      "txrx": ["TX"],
      "suppressed": [false]
    },
    {
      "licenceID": [241123],
      "licenceNumber": [297268],
      "licensee": ["TWO DEGREES NETWORKS LIMITED"],
      "channel": {},
      "frequency": [939.9],
      "location": ["(STH-073-050-A)[VCTS]_S_CATLINS SOUTH PA"],
      "gridRefDefault": ["LAT_LONG_NZGD2000_D2000"],
      "gridReference": ["-46.3797383 169.3932975"],
      "licenceType": ["Other (Spectrum)"],
      "status": ["Current"],
      "txrx": ["RX"],
      "suppressed": [false]
    },
    {
      "licenceID": [241123],
      "licenceNumber": [297268],
      "licensee": ["TWO DEGREES NETWORKS LIMITED"],
      "channel": {},
      "frequency": [939.9],
      "location": ["(STH-073-050-A)[VCTS]_S_CATLINS SOUTH"],
      "gridRefDefault": ["LAT_LONG_NZGD2000_D2000"],
      "gridReference": ["-46.6361092 168.9842819"],
      "licenceType": ["Other (Spectrum)"],
      "status": ["Current"],
      "txrx": ["TX"],
      "suppressed": [false]
    },
    {
      "licenceID": [241122],
      "licenceNumber": [297241],
      "licensee": ["TWO DEGREES NETWORKS LIMITED"],
      "channel": {},
      "frequency": [939.9],
      "location": ["(MNW-036-028-A)[VTNN]_S_TAUMARUNUI NORTH PA"],
      "gridRefDefault": ["LAT_LONG_NZGD2000_D2000"],
      "gridReference": ["-38.4793646 175.5529832"],
      "licenceType": ["Other (Spectrum)"],
      "status": ["Current"],
      "txrx": ["RX"],
      "suppressed": [false]
    },
    {
      "licenceID": [241122],
      "licenceNumber": [297241],
      "licensee": ["TWO DEGREES NETWORKS LIMITED"],
      "channel": {},
      "frequency": [939.9],
      "location": ["(MNW-036-028-A)[VTNN]_S_TAUMARUNUI NORTH"],
      "gridRefDefault": ["LAT_LONG_NZGD2000_D2000"],
      "gridReference": ["-38.7565095 175.2176307"],
      "licenceType": ["Other (Spectrum)"],
      "status": ["Current"],
      "txrx": ["TX"],
      "suppressed": [false]
    },
    {
      "licenceID": [241121],
      "licenceNumber": [297316],
      "licensee": ["TWO DEGREES NETWORKS LIMITED"],
      "channel": {},
      "frequency": [939.9],
      "location": ["(OTG-072-016-A)[VBEM]_S_BEAUMONT PA"],
      "gridRefDefault": ["LAT_LONG_NZGD2000_D2000"],
      "gridReference": ["-45.6061744 169.8148100"],
      "licenceType": ["Other (Spectrum)"],
      "status": ["Current"],
      "txrx": ["RX"],
      "suppressed": [false]
    },
    {
      "licenceID": [241121],
      "licenceNumber": [297316],
      "licensee": ["TWO DEGREES NETWORKS LIMITED"],
      "channel": {},
      "frequency": [939.9],
      "location": ["(OTG-072-016-A)[VBEM]_S_BEAUMONT"],
      "gridRefDefault": ["LAT_LONG_NZGD2000_D2000"],
      "gridReference": ["-45.8643044 169.4135796"],
      "licenceType": ["Other (Spectrum)"],
      "status": ["Current"],
      "txrx": ["TX"],
      "suppressed": [false]
    },
    {
      "licenceID": [241120],
      "licenceNumber": [297288],
      "licensee": ["TWO DEGREES NETWORKS LIMITED"],
      "channel": {},
      "frequency": [939.9],
      "location": ["(WKT-017-021-A)[VWPS]_S_WHAREPAPA SOUTH PA"],
      "gridRefDefault": ["LAT_LONG_NZGD2000_D2000"],
      "gridReference": ["-37.8583762 175.8516527"],
      "licenceType": ["Other (Spectrum)"],
      "status": ["Current"],
      "txrx": ["RX"],
      "suppressed": [false]
    },
    {
      "licenceID": [241120],
      "licenceNumber": [297288],
      "licensee": ["TWO DEGREES NETWORKS LIMITED"],
      "channel": {},
      "frequency": [939.9],
      "location": ["(WKT-017-021-A)[VWPS]_S_WHAREPAPA SOUTH"],
      "gridRefDefault": ["LAT_LONG_NZGD2000_D2000"],
      "gridReference": ["-38.1362630 175.5201993"],
      "licenceType": ["Other (Spectrum)"],
      "status": ["Current"],
      "txrx": ["TX"],
      "suppressed": [false]
    },
    {
      "licenceID": [241119],
      "licenceNumber": [297499],
      "licensee": ["TWO DEGREES NETWORKS LIMITED"],
      "channel": {},
      "frequency": [939.9],
      "location": ["(WST-055-022-A)[VSJC]_S_SPRINGS JUNCTION PA"],
      "gridRefDefault": ["LAT_LONG_NZGD2000_D2000"],
      "gridReference": ["-41.9561601 172.5850594"],
      "licenceType": ["Other (Spectrum)"],
      "status": ["Current"],
      "txrx": ["RX"],
      "suppressed": [false]
    },
    {
      "licenceID": [241119],
      "licenceNumber": [297499],
      "licensee": ["TWO DEGREES NETWORKS LIMITED"],
      "channel": {},
      "frequency": [939.9],
      "location": ["(WST-055-022-A)[VSJC]_S_SPRINGS JUNCTION"],
      "gridRefDefault": ["LAT_LONG_NZGD2000_D2000"],
      "gridReference": ["-42.2244515 172.2197918"],
      "licenceType": ["Other (Spectrum)"],
      "status": ["Current"],
      "txrx": ["TX"],
      "suppressed": [false]
    },
    {
      "licenceID": [241118],
      "licenceNumber": [297489],
      "licensee": ["TWO DEGREES NETWORKS LIMITED"],
      "channel": {},
      "frequency": [939.9],
      "location": ["(MBN-051-042-A)[VTSO]_S_TAPAWERA SOUTH PA"],
      "gridRefDefault": ["LAT_LONG_NZGD2000_D2000"],
      "gridReference": ["-41.1703099 173.1554396"],
      "licenceType": ["Other (Spectrum)"],
      "status": ["Current"],
      "txrx": ["RX"],
      "suppressed": [false]
    },
    {
      "licenceID": [241118],
      "licenceNumber": [297489],
      "licensee": ["TWO DEGREES NETWORKS LIMITED"],
      "channel": {},
      "frequency": [939.9],
      "location": ["(MBN-051-042-A)[VTSO]_S_TAPAWERA SOUTH"],
      "gridRefDefault": ["LAT_LONG_NZGD2000_D2000"],
      "gridReference": ["-41.4404710 172.7969735"],
      "licenceType": ["Other (Spectrum)"],
      "status": ["Current"],
      "txrx": ["TX"],
      "suppressed": [false]
    },
    {
      "licenceID": [241117],
      "licenceNumber": [297559],
      "licensee": ["TWO DEGREES NETWORKS LIMITED"],
      "channel": {},
      "frequency": [939.9],
      "location": ["(MBN-051-039-A)[VMTU]_S_MT MURCHISON PA"],
      "gridRefDefault": ["LAT_LONG_NZGD2000_D2000"],
      "gridReference": ["-41.4599923 172.8605625"],
      "licenceType": ["Other (Spectrum)"],
      "status": ["Current"],
      "txrx": ["RX"],
      "suppressed": [false]
    },
    {
      "licenceID": [241117],
      "licenceNumber": [297559],
      "licensee": ["TWO DEGREES NETWORKS LIMITED"],
      "channel": {},
      "frequency": [939.9],
      "location": ["(MBN-051-039-A)[VMTU]_S_MT MURCHISON"],
      "gridRefDefault": ["LAT_LONG_NZGD2000_D2000"],
      "gridReference": ["-41.7292005 172.4992655"],
      "licenceType": ["Other (Spectrum)"],
      "status": ["Current"],
      "txrx": ["TX"],
      "suppressed": [false]
    },
    {
      "licenceID": [241116],
      "licenceNumber": [297540],
      "licensee": ["TWO DEGREES NETWORKS LIMITED"],
      "channel": {},
      "frequency": [939.9],
      "location": ["(WKT-020-018-A)[VWBR]_S_WAITOMO HOTEL PA"],
      "gridRefDefault": ["LAT_LONG_NZGD2000_D2000"],
      "gridReference": ["-37.9880857 175.4476626"],
      "licenceType": ["Other (Spectrum)"],
      "status": ["Current"],
      "txrx": ["RX"],
      "suppressed": [false]
    },
    {
      "licenceID": [241116],
      "licenceNumber": [297540],
      "licensee": ["TWO DEGREES NETWORKS LIMITED"],
      "channel": {},
      "frequency": [939.9],
      "location": ["(WKT-020-018-A)[VWBR]_S_WAITOMO HOTEL"],
      "gridRefDefault": ["LAT_LONG_NZGD2000_D2000"],
      "gridReference": ["-38.2648931 175.1140645"],
      "licenceType": ["Other (Spectrum)"],
      "status": ["Current"],
      "txrx": ["TX"],
      "suppressed": [false]
    },
    {
      "licenceID": [241115],
      "licenceNumber": [297349],
      "licensee": ["TWO DEGREES NETWORKS LIMITED"],
      "channel": {},
      "frequency": [939.9],
      "location": ["(WKT-020-019-A)[VTMM]_S_TAUMATAMAIRE PA"],
      "gridRefDefault": ["LAT_LONG_NZGD2000_D2000"],
      "gridReference": ["-38.3486912 175.0561692"],
      "licenceType": ["Other (Spectrum)"],
      "status": ["Current"],
      "txrx": ["RX"],
      "suppressed": [false]
    },
    {
      "licenceID": [241115],
      "licenceNumber": [297349],
      "licensee": ["TWO DEGREES NETWORKS LIMITED"],
      "channel": {},
      "frequency": [939.9],
      "location": ["(WKT-020-019-A)[VTMM]_S_TAUMATAMAIRE"],
      "gridRefDefault": ["LAT_LONG_NZGD2000_D2000"],
      "gridReference": ["-38.6244551 174.7194227"],
      "licenceType": ["Other (Spectrum)"],
      "status": ["Current"],
      "txrx": ["TX"],
      "suppressed": [false]
    },
    {
      "licenceID": [241114],
      "licenceNumber": [297498],
      "licensee": ["TWO DEGREES NETWORKS LIMITED"],
      "channel": {},
      "frequency": [939.9],
      "location": ["(MBN-051-044-A)[VWFD]_S_WAKEFIELD PA"],
      "gridRefDefault": ["LAT_LONG_NZGD2000_D2000"],
      "gridReference": ["-41.1257269 173.3942979"],
      "licenceType": ["Other (Spectrum)"],
      "status": ["Current"],
      "txrx": ["RX"],
      "suppressed": [false]
    },
    {
      "licenceID": [241114],
      "licenceNumber": [297498],
      "licensee": ["TWO DEGREES NETWORKS LIMITED"],
      "channel": {},
      "frequency": [939.9],
      "location": ["(MBN-051-044-A)[VWFD]_S_WAKEFIELD"],
      "gridRefDefault": ["LAT_LONG_NZGD2000_D2000"],
      "gridReference": ["-41.3966291 173.0370640"],
      "licenceType": ["Other (Spectrum)"],
      "status": ["Current"],
      "txrx": ["TX"],
      "suppressed": [false]
    },
    {
      "licenceID": [241113],
      "licenceNumber": [297481],
      "licensee": ["TWO DEGREES NETWORKS LIMITED"],
      "channel": {},
      "frequency": [939.9],
      "location": ["(WKT-020-015-A)[VMOK]_S_MOKAU SOUTH PA"],
      "gridRefDefault": ["LAT_LONG_NZGD2000_D2000"],
      "gridReference": ["-38.4331501 174.9540962"],
      "licenceType": ["Other (Spectrum)"],
      "status": ["Current"],
      "txrx": ["RX"],
      "suppressed": [false]
    },
    {
      "licenceID": [241113],
      "licenceNumber": [297481],
      "licensee": ["TWO DEGREES NETWORKS LIMITED"],
      "channel": {},
      "frequency": [939.9],
      "location": ["(WKT-020-015-A)[VMOK]_S_MOKAU SOUTH"],
      "gridRefDefault": ["LAT_LONG_NZGD2000_D2000"],
      "gridReference": ["-38.7086280 174.6165669"],
      "licenceType": ["Other (Spectrum)"],
      "status": ["Current"],
      "txrx": ["TX"],
      "suppressed": [false]
    },
    {
      "licenceID": [241112],
      "licenceNumber": [297337],
      "licensee": ["TWO DEGREES NETWORKS LIMITED"],
      "channel": {},
      "frequency": [939.9],
      "location": ["(WST-057-028-A)[VWHR]_S_WHATAROA PA"],
      "gridRefDefault": ["LAT_LONG_NZGD2000_D2000"],
      "gridReference": ["-42.9045913 170.8429805"],
      "licenceType": ["Other (Spectrum)"],
      "status": ["Current"],
      "txrx": ["RX"],
      "suppressed": [false]
    },
    {
      "licenceID": [241112],
      "licenceNumber": [297337],
      "licensee": ["TWO DEGREES NETWORKS LIMITED"],
      "channel": {},
      "frequency": [939.9],
      "location": ["(WST-057-028-A)[VWHR]_S_WHATAROA"],
      "gridRefDefault": ["LAT_LONG_NZGD2000_D2000"],
      "gridReference": ["-43.1669703 170.4647223"],
      "licenceType": ["Other (Spectrum)"],
      "status": ["Current"],
      "txrx": ["TX"],
      "suppressed": [false]
    },
    {
      "licenceID": [241111],
      "licenceNumber": [297433],
      "licensee": ["TWO DEGREES NETWORKS LIMITED"],
      "channel": {},
      "frequency": [939.9],
      "location": ["(WST-057-024-A)[VFOX]_S_FOX GLACIER PA"],
      "gridRefDefault": ["LAT_LONG_NZGD2000_D2000"],
      "gridReference": ["-43.2035361 170.3994649"],
      "licenceType": ["Other (Spectrum)"],
      "status": ["Current"],
      "txrx": ["RX"],
      "suppressed": [false]
    },
    {
      "licenceID": [241111],
      "licenceNumber": [297433],
      "licensee": ["TWO DEGREES NETWORKS LIMITED"],
      "channel": {},
      "frequency": [939.9],
      "location": ["(WST-057-024-A)[VFOX]_S_FOX GLACIER"],
      "gridRefDefault": ["LAT_LONG_NZGD2000_D2000"],
      "gridReference": ["-43.4643273 170.0174679"],
      "licenceType": ["Other (Spectrum)"],
      "status": ["Current"],
      "txrx": ["TX"],
      "suppressed": [false]
    },
    {
      "licenceID": [241110],
      "licenceNumber": [297521],
      "licensee": ["TWO DEGREES NETWORKS LIMITED"],
      "channel": {},
      "frequency": [939.9],
      "location": ["(CAN-062-022-A)[VARP]_S_ARTHURS PASS PA"],
      "gridRefDefault": ["LAT_LONG_NZGD2000_D2000"],
      "gridReference": ["-42.6747154 171.9352846"],
      "licenceType": ["Other (Spectrum)"],
      "status": ["Current"],
      "txrx": ["RX"],
      "suppressed": [false]
    },
    {
      "licenceID": [241110],
      "licenceNumber": [297521],
      "licensee": ["TWO DEGREES NETWORKS LIMITED"],
      "channel": {},
      "frequency": [939.9],
      "location": ["(CAN-062-022-A)[VARP]_S_ARTHURS PASS"],
      "gridRefDefault": ["LAT_LONG_NZGD2000_D2000"],
      "gridReference": ["-42.9408073 171.5630067"],
      "licenceType": ["Other (Spectrum)"],
      "status": ["Current"],
      "txrx": ["TX"],
      "suppressed": [false]
    },
    {
      "licenceID": [241109],
      "licenceNumber": [297412],
      "licensee": ["TWO DEGREES NETWORKS LIMITED"],
      "channel": {},
      "frequency": [939.9],
      "location": ["(WKT-020-014-A)[VARW]_S_ARIA PA"],
      "gridRefDefault": ["LAT_LONG_NZGD2000_D2000"],
      "gridReference": ["-38.2651204 175.3358935"],
      "licenceType": ["Other (Spectrum)"],
      "status": ["Current"],
      "txrx": ["RX"],
      "suppressed": [false]
    },
    {
      "licenceID": [241109],
      "licenceNumber": [297412],
      "licensee": ["TWO DEGREES NETWORKS LIMITED"],
      "channel": {},
      "frequency": [939.9],
      "location": ["(WKT-020-014-A)[VARW]_S_ARIA"],
      "gridRefDefault": ["LAT_LONG_NZGD2000_D2000"],
      "gridReference": ["-38.5416447 175.0006268"],
      "licenceType": ["Other (Spectrum)"],
      "status": ["Current"],
      "txrx": ["TX"],
      "suppressed": [false]
    },
    {
      "licenceID": [241108],
      "licenceNumber": [297387],
      "licensee": ["TWO DEGREES NETWORKS LIMITED"],
      "channel": {},
      "frequency": [939.9],
      "location": ["(WKT-020-017-A)[VPIO]_S_PIOPIO (WAIKATO) PA"],
      "gridRefDefault": ["LAT_LONG_NZGD2000_D2000"],
      "gridReference": ["-38.1933054 175.4023533"],
      "licenceType": ["Other (Spectrum)"],
      "status": ["Current"],
      "txrx": ["RX"],
      "suppressed": [false]
    },
    {
      "licenceID": [241108],
      "licenceNumber": [297387],
      "licensee": ["TWO DEGREES NETWORKS LIMITED"],
      "channel": {},
      "frequency": [939.9],
      "location": ["(WKT-020-017-A)[VPIO]_S_PIOPIO (WAIKATO)"],
      "gridRefDefault": ["LAT_LONG_NZGD2000_D2000"],
      "gridReference": ["-38.4700060 175.0676728"],
      "licenceType": ["Other (Spectrum)"],
      "status": ["Current"],
      "txrx": ["TX"],
      "suppressed": [false]
    },
    {
      "licenceID": [241107],
      "licenceNumber": [297471],
      "licensee": ["TWO DEGREES NETWORKS LIMITED"],
      "channel": {},
      "frequency": [939.9],
      "location": ["(WKT-020-013-A)[VBYL]_S_BENNEYDALE PA"],
      "gridRefDefault": ["LAT_LONG_NZGD2000_D2000"],
      "gridReference": ["-38.7988444 175.7129510"],
      "licenceType": ["Other (Spectrum)"],
      "status": ["Current"],
      "txrx": ["RX"],
      "suppressed": [false]
    },
    {
      "licenceID": [241107],
      "licenceNumber": [297471],
      "licensee": ["TWO DEGREES NETWORKS LIMITED"],
      "channel": {},
      "frequency": [939.9],
      "location": ["(WKT-020-013-A)[VBYL]_S_BENNEYDALE"],
      "gridRefDefault": ["LAT_LONG_NZGD2000_D2000"],
      "gridReference": ["-38.5362249 175.3589051"],
      "licenceType": ["Other (Spectrum)"],
      "status": ["Current"],
      "txrx": ["TX"],
      "suppressed": [false]
    },
    {
      "licenceID": [241106],
      "licenceNumber": [297372],
      "licensee": ["TWO DEGREES NETWORKS LIMITED"],
      "channel": {},
      "frequency": [939.9],
      "location": ["(WKT-018-012-A)[VKHA]_S_KAWHIA PA"],
      "gridRefDefault": ["LAT_LONG_NZGD2000_D2000"],
      "gridReference": ["-37.7645293 175.2174801"],
      "licenceType": ["Other (Spectrum)"],
      "status": ["Current"],
      "txrx": ["RX"],
      "suppressed": [false]
    },
    {
      "licenceID": [241106],
      "licenceNumber": [297372],
      "licensee": ["TWO DEGREES NETWORKS LIMITED"],
      "channel": {},
      "frequency": [939.9],
      "location": ["(WKT-018-012-A)[VKHA]_S_KAWHIA"],
      "gridRefDefault": ["LAT_LONG_NZGD2000_D2000"],
      "gridReference": ["-38.0406890 174.8839518"],
      "licenceType": ["Other (Spectrum)"],
      "status": ["Current"],
      "txrx": ["TX"],
      "suppressed": [false]
    },
    {
      "licenceID": [241105],
      "licenceNumber": [297517],
      "licensee": ["TWO DEGREES NETWORKS LIMITED"],
      "channel": {},
      "frequency": [939.9],
      "location": ["(WKT-018-014-A)[VOTE]_S_OTEWA PA"],
      "gridRefDefault": ["LAT_LONG_NZGD2000_D2000"],
      "gridReference": ["-37.9460870 175.6428363"],
      "licenceType": ["Other (Spectrum)"],
      "status": ["Current"],
      "txrx": ["RX"],
      "suppressed": [false]
    },
    {
      "licenceID": [241105],
      "licenceNumber": [297517],
      "licensee": ["TWO DEGREES NETWORKS LIMITED"],
      "channel": {},
      "frequency": [939.9],
      "location": ["(WKT-018-014-A)[VOTE]_S_OTEWA"],
      "gridRefDefault": ["LAT_LONG_NZGD2000_D2000"],
      "gridReference": ["-38.2234235 175.3101882"],
      "licenceType": ["Other (Spectrum)"],
      "status": ["Current"],
      "txrx": ["TX"],
      "suppressed": [false]
    },
    {
      "licenceID": [241104],
      "licenceNumber": [297361],
      "licensee": ["TWO DEGREES NETWORKS LIMITED"],
      "channel": {},
      "frequency": [939.9],
      "location": ["(WST-055-023-A)[VWPT]_S_WESTPORT (BCL) PA"],
      "gridRefDefault": ["LAT_LONG_NZGD2000_D2000"],
      "gridReference": ["-41.5119591 172.1044705"],
      "licenceType": ["Other (Spectrum)"],
      "status": ["Current"],
      "txrx": ["RX"],
      "suppressed": [false]
    },
    {
      "licenceID": [241104],
      "licenceNumber": [297361],
      "licensee": ["TWO DEGREES NETWORKS LIMITED"],
      "channel": {},
      "frequency": [939.9],
      "location": ["(WST-055-023-A)[VWPT]_S_WESTPORT (BCL)"],
      "gridRefDefault": ["LAT_LONG_NZGD2000_D2000"],
      "gridReference": ["-41.7787508 171.7397858"],
      "licenceType": ["Other (Spectrum)"],
      "status": ["Current"],
      "txrx": ["TX"],
      "suppressed": [false]
    },
    {
      "licenceID": [241103],
      "licenceNumber": [297467],
      "licensee": ["TWO DEGREES NETWORKS LIMITED"],
      "channel": {},
      "frequency": [939.9],
      "location": ["(WLG-048-015-A)[VCPT]_S_CASTLE POINT RBI PA"],
      "gridRefDefault": ["LAT_LONG_NZGD2000_D2000"],
      "gridReference": ["-40.5697426 176.5673918"],
      "licenceType": ["Other (Spectrum)"],
      "status": ["Current"],
      "txrx": ["RX"],
      "suppressed": [false]
    },
    {
      "licenceID": [241103],
      "licenceNumber": [297467],
      "licensee": ["TWO DEGREES NETWORKS LIMITED"],
      "channel": {},
      "frequency": [939.9],
      "location": ["(WLG-048-015-A)[VCPT]_S_CASTLE POINT RBI"],
      "gridRefDefault": ["LAT_LONG_NZGD2000_D2000"],
      "gridReference": ["-40.8499724 176.2265805"],
      "licenceType": ["Other (Spectrum)"],
      "status": ["Current"],
      "txrx": ["TX"],
      "suppressed": [false]
    },
    {
      "licenceID": [241102],
      "licenceNumber": [297418],
      "licensee": ["TWO DEGREES NETWORKS LIMITED"],
      "channel": {},
      "frequency": [939.9],
      "location": ["(WKT-018-013-A)[VMHH]_S_MAIHIIHI PA"],
      "gridRefDefault": ["LAT_LONG_NZGD2000_D2000"],
      "gridReference": ["-37.9412893 175.6993370"],
      "licenceType": ["Other (Spectrum)"],
      "status": ["Current"],
      "txrx": ["RX"],
      "suppressed": [false]
    },
    {
      "licenceID": [241102],
      "licenceNumber": [297418],
      "licensee": ["TWO DEGREES NETWORKS LIMITED"],
      "channel": {},
      "frequency": [939.9],
      "location": ["(WKT-018-013-A)[VMHH]_S_MAIHIIHI"],
      "gridRefDefault": ["LAT_LONG_NZGD2000_D2000"],
      "gridReference": ["-38.2187741 175.3669325"],
      "licenceType": ["Other (Spectrum)"],
      "status": ["Current"],
      "txrx": ["TX"],
      "suppressed": [false]
    },
    {
      "licenceID": [241101],
      "licenceNumber": [297386],
      "licensee": ["TWO DEGREES NETWORKS LIMITED"],
      "channel": {},
      "frequency": [939.9],
      "location": ["(MNW-036-026-A)[VTGW]_S_TANGIWAI PA"],
      "gridRefDefault": ["LAT_LONG_NZGD2000_D2000"],
      "gridReference": ["-39.2114706 175.8639912"],
      "licenceType": ["Other (Spectrum)"],
      "status": ["Current"],
      "txrx": ["RX"],
      "suppressed": [false]
    },
    {
      "licenceID": [241101],
      "licenceNumber": [297386],
      "licensee": ["TWO DEGREES NETWORKS LIMITED"],
      "channel": {},
      "frequency": [939.9],
      "location": ["(MNW-036-026-A)[VTGW]_S_TANGIWAI"],
      "gridRefDefault": ["LAT_LONG_NZGD2000_D2000"],
      "gridReference": ["-39.4895582 175.5265855"],
      "licenceType": ["Other (Spectrum)"],
      "status": ["Current"],
      "txrx": ["TX"],
      "suppressed": [false]
    },
    {
      "licenceID": [241100],
      "licenceNumber": [297550],
      "licensee": ["TWO DEGREES NETWORKS LIMITED"],
      "channel": {},
      "frequency": [939.9],
      "location": ["(HKB-030-016-A)[VWMR]_S_WAIMARAMA PA"],
      "gridRefDefault": ["LAT_LONG_NZGD2000_D2000"],
      "gridReference": ["-39.5073383 177.3117583"],
      "licenceType": ["Other (Spectrum)"],
      "status": ["Current"],
      "txrx": ["RX"],
      "suppressed": [false]
    },
    {
      "licenceID": [241100],
      "licenceNumber": [297550],
      "licensee": ["TWO DEGREES NETWORKS LIMITED"],
      "channel": {},
      "frequency": [939.9],
      "location": ["(HKB-030-016-A)[VWMR]_S_WAIMARAMA"],
      "gridRefDefault": ["LAT_LONG_NZGD2000_D2000"],
      "gridReference": ["-39.7894054 176.9791333"],
      "licenceType": ["Other (Spectrum)"],
      "status": ["Current"],
      "txrx": ["TX"],
      "suppressed": [false]
    },
    {
      "licenceID": [241099],
      "licenceNumber": [297438],
      "licensee": ["TWO DEGREES NETWORKS LIMITED"],
      "channel": {},
      "frequency": [939.9],
      "location": ["(TNK-033-032-A)[VFZY]_S_FITZROY PA"],
      "gridRefDefault": ["LAT_LONG_NZGD2000_D2000"],
      "gridReference": ["-38.7728513 174.4612872"],
      "licenceType": ["Other (Spectrum)"],
      "status": ["Current"],
      "txrx": ["RX"],
      "suppressed": [false]
    },
    {
      "licenceID": [241099],
      "licenceNumber": [297438],
      "licensee": ["TWO DEGREES NETWORKS LIMITED"],
      "channel": {},
      "frequency": [939.9],
      "location": ["(TNK-033-032-A)[VFZY]_S_FITZROY"],
      "gridRefDefault": ["LAT_LONG_NZGD2000_D2000"],
      "gridReference": ["-39.0469533 174.1202552"],
      "licenceType": ["Other (Spectrum)"],
      "status": ["Current"],
      "txrx": ["TX"],
      "suppressed": [false]
    },
    {
      "licenceID": [241098],
      "licenceNumber": [297397],
      "licensee": ["TWO DEGREES NETWORKS LIMITED"],
      "channel": {},
      "frequency": [939.9],
      "location": ["(HKB-032-013-A)[VTKR]_S_TAKAPAU PA"],
      "gridRefDefault": ["LAT_LONG_NZGD2000_D2000"],
      "gridReference": ["-39.8160569 176.6580623"],
      "licenceType": ["Other (Spectrum)"],
      "status": ["Current"],
      "txrx": ["RX"],
      "suppressed": [false]
    },
    {
      "licenceID": [241098],
      "licenceNumber": [297397],
      "licensee": ["TWO DEGREES NETWORKS LIMITED"],
      "channel": {},
      "frequency": [939.9],
      "location": ["(HKB-032-013-A)[VTKR]_S_TAKAPAU"],
      "gridRefDefault": ["LAT_LONG_NZGD2000_D2000"],
      "gridReference": ["-40.0964129 176.3212191"],
      "licenceType": ["Other (Spectrum)"],
      "status": ["Current"],
      "txrx": ["TX"],
      "suppressed": [false]
    },
    {
      "licenceID": [241097],
      "licenceNumber": [297443],
      "licensee": ["TWO DEGREES NETWORKS LIMITED"],
      "channel": {},
      "frequency": [939.9],
      "location": ["(HKB-030-013-A)[VTTA]_S_TATARAAKINA (BCL) PA"],
      "gridRefDefault": ["LAT_LONG_NZGD2000_D2000"],
      "gridReference": ["-38.7689394 176.9623304"],
      "licenceType": ["Other (Spectrum)"],
      "status": ["Current"],
      "txrx": ["RX"],
      "suppressed": [false]
    },
    {
      "licenceID": [241097],
      "licenceNumber": [297443],
      "licensee": ["TWO DEGREES NETWORKS LIMITED"],
      "channel": {},
      "frequency": [939.9],
      "location": ["(HKB-030-013-A)[VTTA]_S_TATARAAKINA (BCL)"],
      "gridRefDefault": ["LAT_LONG_NZGD2000_D2000"],
      "gridReference": ["-39.0499290 176.6314703"],
      "licenceType": ["Other (Spectrum)"],
      "status": ["Current"],
      "txrx": ["TX"],
      "suppressed": [false]
    },
    {
      "licenceID": [241096],
      "licenceNumber": [297480],
      "licensee": ["TWO DEGREES NETWORKS LIMITED"],
      "channel": {},
      "frequency": [939.9],
      "location": ["(HKB-030-017 -A)[VPTO]_S_PATOKA PA"],
      "gridRefDefault": ["LAT_LONG_NZGD2000_D2000"],
      "gridReference": ["-39.0530713 176.9315169"],
      "licenceType": ["Other (Spectrum)"],
      "status": ["Current"],
      "txrx": ["RX"],
      "suppressed": [false]
    },
    {
      "licenceID": [241096],
      "licenceNumber": [297480],
      "licensee": ["TWO DEGREES NETWORKS LIMITED"],
      "channel": {},
      "frequency": [939.9],
      "location": ["(HKB-030-017 -A)[VPTO]_S_PATOKA"],
      "gridRefDefault": ["LAT_LONG_NZGD2000_D2000"],
      "gridReference": ["-39.3340411 176.5992813"],
      "licenceType": ["Other (Spectrum)"],
      "status": ["Current"],
      "txrx": ["TX"],
      "suppressed": [false]
    },
    {
      "licenceID": [241095],
      "licenceNumber": [297376],
      "licensee": ["TWO DEGREES NETWORKS LIMITED"],
      "channel": {},
      "frequency": [939.9],
      "location": ["(MNW-036-025-A)[VRNP]_S_RUAPEHU PA"],
      "gridRefDefault": ["LAT_LONG_NZGD2000_D2000"],
      "gridReference": ["-38.8886995 175.7328524"],
      "licenceType": ["Other (Spectrum)"],
      "status": ["Current"],
      "txrx": ["RX"],
      "suppressed": [false]
    },
    {
      "licenceID": [241095],
      "licenceNumber": [297376],
      "licensee": ["TWO DEGREES NETWORKS LIMITED"],
      "channel": {},
      "frequency": [939.9],
      "location": ["(MNW-036-025-A)[VRNP]_S_RUAPEHU"],
      "gridRefDefault": ["LAT_LONG_NZGD2000_D2000"],
      "gridReference": ["-39.1663871 175.3963800"],
      "licenceType": ["Other (Spectrum)"],
      "status": ["Current"],
      "txrx": ["TX"],
      "suppressed": [false]
    }
  ],
  "links": []
}
