{
  "pageSize": [100],
  "page": [21],
  "totalItems": [3283],
  "totalPages": [33],
  "sortBy": ["Licence ID"],
  "sortOrder": ["desc"],
  "items": [
    {
      "licenceID": [220352],
      "licenceNumber": [280773],
      "licensee": ["SPARK NEW ZEALAND TRADING LIMITED"],
      "channel": {},
      "frequency": [2665],
      "location": ["LANSDOWNE P A"],
      "gridRefDefault": ["LAT_LONG_NZGD2000_D2000"],
      "gridReference": ["-40.8618413 175.5365850"],
      "licenceType": ["Other (Spectrum)"],
      "status": ["Current"],
      "txrx": ["RX"],
      "suppressed": [false]
    },
    {
      "licenceID": [220352],
      "licenceNumber": [280773],
      "licensee": ["SPARK NEW ZEALAND TRADING LIMITED"],
      "channel": {},
      "frequency": [2665],
      "location": ["LANSDOWNE"],
      "gridRefDefault": ["LAT_LONG_NZGD2000_D2000"],
      "gridReference": ["-40.9491883 175.6731387"],
      "licenceType": ["Other (Spectrum)"],
      "status": ["Current"],
      "txrx": ["TX"],
      "suppressed": [false]
    },
    {
      "licenceID": [220351],
      "licenceNumber": [280840],
      "licensee": ["SPARK NEW ZEALAND TRADING LIMITED"],
      "channel": {},
      "frequency": [2665],
      "location": ["INGLEWOOD TOWN P A"],
      "gridRefDefault": ["LAT_LONG_NZGD2000_D2000"],
      "gridReference": ["-39.0659118 174.0867132"],
      "licenceType": ["Other (Spectrum)"],
      "status": ["Current"],
      "txrx": ["RX"],
      "suppressed": [false]
    },
    {
      "licenceID": [220351],
      "licenceNumber": [280840],
      "licensee": ["SPARK NEW ZEALAND TRADING LIMITED"],
      "channel": {},
      "frequency": [2665],
      "location": ["INGLEWOOD TOWN"],
      "gridRefDefault": ["LAT_LONG_NZGD2000_D2000"],
      "gridReference": ["-39.1540861 174.2042925"],
      "licenceType": ["Other (Spectrum)"],
      "status": ["Current"],
      "txrx": ["TX"],
      "suppressed": [false]
    },
    {
      "licenceID": [220350],
      "licenceNumber": [281081],
      "licensee": ["SPARK NEW ZEALAND TRADING LIMITED"],
      "channel": {},
      "frequency": [2665],
      "location": ["HAUMOANA P A"],
      "gridRefDefault": ["LAT_LONG_NZGD2000_D2000"],
      "gridReference": ["-39.5617504 176.8309250"],
      "licenceType": ["Other (Spectrum)"],
      "status": ["Current"],
      "txrx": ["RX"],
      "suppressed": [false]
    },
    {
      "licenceID": [220350],
      "licenceNumber": [281081],
      "licensee": ["SPARK NEW ZEALAND TRADING LIMITED"],
      "channel": {},
      "frequency": [2665],
      "location": ["HAUMOANA"],
      "gridRefDefault": ["LAT_LONG_NZGD2000_D2000"],
      "gridReference": ["-39.6476059 176.9525154"],
      "licenceType": ["Other (Spectrum)"],
      "status": ["Current"],
      "txrx": ["TX"],
      "suppressed": [false]
    },
    {
      "licenceID": [220349],
      "licenceNumber": [280889],
      "licensee": ["SPARK NEW ZEALAND TRADING LIMITED"],
      "channel": {},
      "frequency": [2665],
      "location": ["HEIGHTS ROAD P A"],
      "gridRefDefault": ["LAT_LONG_NZGD2000_D2000"],
      "gridReference": ["-40.4924278 175.2795316"],
      "licenceType": ["Other (Spectrum)"],
      "status": ["Current"],
      "txrx": ["RX"],
      "suppressed": [false]
    },
    {
      "licenceID": [220349],
      "licenceNumber": [280889],
      "licensee": ["SPARK NEW ZEALAND TRADING LIMITED"],
      "channel": {},
      "frequency": [2665],
      "location": ["HEIGHTS ROAD"],
      "gridRefDefault": ["LAT_LONG_NZGD2000_D2000"],
      "gridReference": ["-40.5796143 175.4017908"],
      "licenceType": ["Other (Spectrum)"],
      "status": ["Current"],
      "txrx": ["TX"],
      "suppressed": [false]
    },
    {
      "licenceID": [220348],
      "licenceNumber": [280871],
      "licensee": ["SPARK NEW ZEALAND TRADING LIMITED"],
      "channel": {},
      "frequency": [2665],
      "location": ["GREYTOWN PA"],
      "gridRefDefault": ["LAT_LONG_NZGD2000_D2000"],
      "gridReference": ["-40.9930056 175.3367886"],
      "licenceType": ["Other (Spectrum)"],
      "status": ["Current"],
      "txrx": ["RX"],
      "suppressed": [false]
    },
    {
      "licenceID": [220348],
      "licenceNumber": [280871],
      "licensee": ["SPARK NEW ZEALAND TRADING LIMITED"],
      "channel": {},
      "frequency": [2665],
      "location": ["GREYTOWN"],
      "gridRefDefault": ["LAT_LONG_NZGD2000_D2000"],
      "gridReference": ["-41.0805990 175.4594052"],
      "licenceType": ["Other (Spectrum)"],
      "status": ["Current"],
      "txrx": ["TX"],
      "suppressed": [false]
    },
    {
      "licenceID": [220347],
      "licenceNumber": [280929],
      "licensee": ["SPARK NEW ZEALAND TRADING LIMITED"],
      "channel": {},
      "frequency": [2665],
      "location": ["FOXTON BEACH P A"],
      "gridRefDefault": ["LAT_LONG_NZGD2000_D2000"],
      "gridReference": ["-40.3802202 175.1166826"],
      "licenceType": ["Other (Spectrum)"],
      "status": ["Current"],
      "txrx": ["RX"],
      "suppressed": [false]
    },
    {
      "licenceID": [220347],
      "licenceNumber": [280929],
      "licensee": ["SPARK NEW ZEALAND TRADING LIMITED"],
      "channel": {},
      "frequency": [2665],
      "location": ["FOXTON BEACH"],
      "gridRefDefault": ["LAT_LONG_NZGD2000_D2000"],
      "gridReference": ["-40.4680203 175.2378047"],
      "licenceType": ["Other (Spectrum)"],
      "status": ["Current"],
      "txrx": ["TX"],
      "suppressed": [false]
    },
    {
      "licenceID": [220346],
      "licenceNumber": [280910],
      "licensee": ["SPARK NEW ZEALAND TRADING LIMITED"],
      "channel": {},
      "frequency": [2665],
      "location": ["FOXTON P A"],
      "gridRefDefault": ["LAT_LONG_NZGD2000_D2000"],
      "gridReference": ["-40.3902142 175.1605937"],
      "licenceType": ["Other (Spectrum)"],
      "status": ["Current"],
      "txrx": ["RX"],
      "suppressed": [false]
    },
    {
      "licenceID": [220346],
      "licenceNumber": [280910],
      "licensee": ["SPARK NEW ZEALAND TRADING LIMITED"],
      "channel": {},
      "frequency": [2665],
      "location": ["FOXTON"],
      "gridRefDefault": ["LAT_LONG_NZGD2000_D2000"],
      "gridReference": ["-40.4781200 175.2819940"],
      "licenceType": ["Other (Spectrum)"],
      "status": ["Current"],
      "txrx": ["TX"],
      "suppressed": [false]
    },
    {
      "licenceID": [220345],
      "licenceNumber": [280951],
      "licensee": ["SPARK NEW ZEALAND TRADING LIMITED"],
      "channel": {},
      "frequency": [2665],
      "location": ["FEILDING P A"],
      "gridRefDefault": ["LAT_LONG_NZGD2000_D2000"],
      "gridReference": ["-40.1280126 175.4315647"],
      "licenceType": ["Other (Spectrum)"],
      "status": ["Current"],
      "txrx": ["RX"],
      "suppressed": [false]
    },
    {
      "licenceID": [220345],
      "licenceNumber": [280951],
      "licensee": ["SPARK NEW ZEALAND TRADING LIMITED"],
      "channel": {},
      "frequency": [2665],
      "location": ["FEILDING"],
      "gridRefDefault": ["LAT_LONG_NZGD2000_D2000"],
      "gridReference": ["-40.2147774 175.5528090"],
      "licenceType": ["Other (Spectrum)"],
      "status": ["Current"],
      "txrx": ["TX"],
      "suppressed": [false]
    },
    {
      "licenceID": [220344],
      "licenceNumber": [280804],
      "licensee": ["SPARK NEW ZEALAND TRADING LIMITED"],
      "channel": {},
      "frequency": [2665],
      "location": ["FEILDING TOWN P A"],
      "gridRefDefault": ["LAT_LONG_NZGD2000_D2000"],
      "gridReference": ["-40.1375677 175.4483442"],
      "licenceType": ["Other (Spectrum)"],
      "status": ["Current"],
      "txrx": ["RX"],
      "suppressed": [false]
    },
    {
      "licenceID": [220344],
      "licenceNumber": [280804],
      "licensee": ["SPARK NEW ZEALAND TRADING LIMITED"],
      "channel": {},
      "frequency": [2665],
      "location": ["FEILDING TOWN"],
      "gridRefDefault": ["LAT_LONG_NZGD2000_D2000"],
      "gridReference": ["-40.2241751 175.5698210"],
      "licenceType": ["Other (Spectrum)"],
      "status": ["Current"],
      "txrx": ["TX"],
      "suppressed": [false]
    },
    {
      "licenceID": [220343],
      "licenceNumber": [280907],
      "licensee": ["SPARK NEW ZEALAND TRADING LIMITED"],
      "channel": {},
      "frequency": [2665],
      "location": ["FEATHERSTON P A"],
      "gridRefDefault": ["LAT_LONG_NZGD2000_D2000"],
      "gridReference": ["-41.0157723 175.1892414"],
      "licenceType": ["Other (Spectrum)"],
      "status": ["Current"],
      "txrx": ["RX"],
      "suppressed": [false]
    },
    {
      "licenceID": [220343],
      "licenceNumber": [280907],
      "licensee": ["SPARK NEW ZEALAND TRADING LIMITED"],
      "channel": {},
      "frequency": [2665],
      "location": ["FEATHERSTON"],
      "gridRefDefault": ["LAT_LONG_NZGD2000_D2000"],
      "gridReference": ["-41.1030816 175.3112058"],
      "licenceType": ["Other (Spectrum)"],
      "status": ["Current"],
      "txrx": ["TX"],
      "suppressed": [false]
    },
    {
      "licenceID": [220342],
      "licenceNumber": [280870],
      "licensee": ["SPARK NEW ZEALAND TRADING LIMITED"],
      "channel": {},
      "frequency": [2665],
      "location": ["FEILDING SOUTH P A"],
      "gridRefDefault": ["LAT_LONG_NZGD2000_D2000"],
      "gridReference": ["-40.1467961 175.4381108"],
      "licenceType": ["Other (Spectrum)"],
      "status": ["Current"],
      "txrx": ["RX"],
      "suppressed": [false]
    },
    {
      "licenceID": [220342],
      "licenceNumber": [280870],
      "licensee": ["SPARK NEW ZEALAND TRADING LIMITED"],
      "channel": {},
      "frequency": [2665],
      "location": ["FEILDING SOUTH"],
      "gridRefDefault": ["LAT_LONG_NZGD2000_D2000"],
      "gridReference": ["-40.2337070 175.5589676"],
      "licenceType": ["Other (Spectrum)"],
      "status": ["Current"],
      "txrx": ["TX"],
      "suppressed": [false]
    },
    {
      "licenceID": [220341],
      "licenceNumber": [280950],
      "licensee": ["SPARK NEW ZEALAND TRADING LIMITED"],
      "channel": {},
      "frequency": [2665],
      "location": ["DANNEVIRKE P A"],
      "gridRefDefault": ["LAT_LONG_NZGD2000_D2000"],
      "gridReference": ["-40.1146229 175.9639307"],
      "licenceType": ["Other (Spectrum)"],
      "status": ["Current"],
      "txrx": ["RX"],
      "suppressed": [false]
    },
    {
      "licenceID": [220341],
      "licenceNumber": [280950],
      "licensee": ["SPARK NEW ZEALAND TRADING LIMITED"],
      "channel": {},
      "frequency": [2665],
      "location": ["DANNEVIRKE"],
      "gridRefDefault": ["LAT_LONG_NZGD2000_D2000"],
      "gridReference": ["-40.2013953 176.0858479"],
      "licenceType": ["Other (Spectrum)"],
      "status": ["Current"],
      "txrx": ["TX"],
      "suppressed": [false]
    },
    {
      "licenceID": [220340],
      "licenceNumber": [280768],
      "licensee": ["SPARK NEW ZEALAND TRADING LIMITED"],
      "channel": {},
      "frequency": [2665],
      "location": ["CARTERTON CENTRAL P A"],
      "gridRefDefault": ["LAT_LONG_NZGD2000_D2000"],
      "gridReference": ["-40.9433865 175.3876260"],
      "licenceType": ["Other (Spectrum)"],
      "status": ["Current"],
      "txrx": ["RX"],
      "suppressed": [false]
    },
    {
      "licenceID": [220340],
      "licenceNumber": [280768],
      "licensee": ["SPARK NEW ZEALAND TRADING LIMITED"],
      "channel": {},
      "frequency": [2665],
      "location": ["CARTERTON CENTRAL"],
      "gridRefDefault": ["LAT_LONG_NZGD2000_D2000"],
      "gridReference": ["-41.0302244 175.5102847"],
      "licenceType": ["Other (Spectrum)"],
      "status": ["Current"],
      "txrx": ["TX"],
      "suppressed": [false]
    },
    {
      "licenceID": [220339],
      "licenceNumber": [281027],
      "licensee": ["SPARK NEW ZEALAND TRADING LIMITED"],
      "channel": {},
      "frequency": [2665],
      "location": ["COLLEGE STREET P A"],
      "gridRefDefault": ["LAT_LONG_NZGD2000_D2000"],
      "gridReference": ["-40.2866731 175.4702264"],
      "licenceType": ["Other (Spectrum)"],
      "status": ["Current"],
      "txrx": ["RX"],
      "suppressed": [false]
    },
    {
      "licenceID": [220339],
      "licenceNumber": [281027],
      "licensee": ["SPARK NEW ZEALAND TRADING LIMITED"],
      "channel": {},
      "frequency": [2665],
      "location": ["COLLEGE STREET"],
      "gridRefDefault": ["LAT_LONG_NZGD2000_D2000"],
      "gridReference": ["-40.3732479 175.5917382"],
      "licenceType": ["Other (Spectrum)"],
      "status": ["Current"],
      "txrx": ["TX"],
      "suppressed": [false]
    },
    {
      "licenceID": [220338],
      "licenceNumber": [281089],
      "licensee": ["SPARK NEW ZEALAND TRADING LIMITED"],
      "channel": {},
      "frequency": [2665],
      "location": ["BULLS P A"],
      "gridRefDefault": ["LAT_LONG_NZGD2000_D2000"],
      "gridReference": ["-40.0751087 175.2419994"],
      "licenceType": ["Other (Spectrum)"],
      "status": ["Current"],
      "txrx": ["RX"],
      "suppressed": [false]
    },
    {
      "licenceID": [220338],
      "licenceNumber": [281089],
      "licensee": ["SPARK NEW ZEALAND TRADING LIMITED"],
      "channel": {},
      "frequency": [2665],
      "location": ["BULLS"],
      "gridRefDefault": ["LAT_LONG_NZGD2000_D2000"],
      "gridReference": ["-40.1619243 175.3631420"],
      "licenceType": ["Other (Spectrum)"],
      "status": ["Current"],
      "txrx": ["TX"],
      "suppressed": [false]
    },
    {
      "licenceID": [220337],
      "licenceNumber": [281034],
      "licensee": ["SPARK NEW ZEALAND TRADING LIMITED"],
      "channel": {},
      "frequency": [2665],
      "location": ["BARRY PARK PA"],
      "gridRefDefault": ["LAT_LONG_NZGD2000_D2000"],
      "gridReference": ["-38.5701410 177.8899849"],
      "licenceType": ["Other (Spectrum)"],
      "status": ["Current"],
      "txrx": ["RX"],
      "suppressed": [false]
    },
    {
      "licenceID": [220337],
      "licenceNumber": [281034],
      "licensee": ["SPARK NEW ZEALAND TRADING LIMITED"],
      "channel": {},
      "frequency": [2665],
      "location": ["BARRY PARK"],
      "gridRefDefault": ["LAT_LONG_NZGD2000_D2000"],
      "gridReference": ["-38.6547155 178.0112926"],
      "licenceType": ["Other (Spectrum)"],
      "status": ["Current"],
      "txrx": ["TX"],
      "suppressed": [false]
    },
    {
      "licenceID": [220336],
      "licenceNumber": [281102],
      "licensee": ["SPARK NEW ZEALAND TRADING LIMITED"],
      "channel": {},
      "frequency": [2665],
      "location": ["BLAGDON HILL P A"],
      "gridRefDefault": ["LAT_LONG_NZGD2000_D2000"],
      "gridReference": ["-38.9809410 173.9225817"],
      "licenceType": ["Other (Spectrum)"],
      "status": ["Current"],
      "txrx": ["RX"],
      "suppressed": [false]
    },
    {
      "licenceID": [220336],
      "licenceNumber": [281102],
      "licensee": ["SPARK NEW ZEALAND TRADING LIMITED"],
      "channel": {},
      "frequency": [2665],
      "location": ["BLAGDON HILL"],
      "gridRefDefault": ["LAT_LONG_NZGD2000_D2000"],
      "gridReference": ["-39.0696453 174.0399918"],
      "licenceType": ["Other (Spectrum)"],
      "status": ["Current"],
      "txrx": ["TX"],
      "suppressed": [false]
    },
    {
      "licenceID": [220335],
      "licenceNumber": [280758],
      "licensee": ["SPARK NEW ZEALAND TRADING LIMITED"],
      "channel": {},
      "frequency": [2665],
      "location": ["BELL BLOCK RELOCATION PA"],
      "gridRefDefault": ["LAT_LONG_NZGD2000_D2000"],
      "gridReference": ["-38.9479665 174.0250844"],
      "licenceType": ["Other (Spectrum)"],
      "status": ["Current"],
      "txrx": ["RX"],
      "suppressed": [false]
    },
    {
      "licenceID": [220335],
      "licenceNumber": [280758],
      "licensee": ["SPARK NEW ZEALAND TRADING LIMITED"],
      "channel": {},
      "frequency": [2665],
      "location": ["BELL BLOCK RELOCATION"],
      "gridRefDefault": ["LAT_LONG_NZGD2000_D2000"],
      "gridReference": ["-39.0369479 174.1424511"],
      "licenceType": ["Other (Spectrum)"],
      "status": ["Current"],
      "txrx": ["TX"],
      "suppressed": [false]
    },
    {
      "licenceID": [220334],
      "licenceNumber": [281022],
      "licensee": ["SPARK NEW ZEALAND TRADING LIMITED"],
      "channel": {},
      "frequency": [2665],
      "location": ["ASHURST PA"],
      "gridRefDefault": ["LAT_LONG_NZGD2000_D2000"],
      "gridReference": ["-40.2111086 175.6273018"],
      "licenceType": ["Other (Spectrum)"],
      "status": ["Current"],
      "txrx": ["RX"],
      "suppressed": [false]
    },
    {
      "licenceID": [220334],
      "licenceNumber": [281022],
      "licensee": ["SPARK NEW ZEALAND TRADING LIMITED"],
      "channel": {},
      "frequency": [2665],
      "location": ["ASHURST"],
      "gridRefDefault": ["LAT_LONG_NZGD2000_D2000"],
      "gridReference": ["-40.2976401 175.7491965"],
      "licenceType": ["Other (Spectrum)"],
      "status": ["Current"],
      "txrx": ["TX"],
      "suppressed": [false]
    },
    {
      "licenceID": [220333],
      "licenceNumber": [280815],
      "licensee": ["SPARK NEW ZEALAND TRADING LIMITED"],
      "channel": {},
      "frequency": [2665],
      "location": ["CARTERTON EXCHANGE P A"],
      "gridRefDefault": ["LAT_LONG_NZGD2000_D2000"],
      "gridReference": ["-40.9403664 175.4029609"],
      "licenceType": ["Other (Spectrum)"],
      "status": ["Current"],
      "txrx": ["RX"],
      "suppressed": [false]
    },
    {
      "licenceID": [220333],
      "licenceNumber": [280815],
      "licensee": ["SPARK NEW ZEALAND TRADING LIMITED"],
      "channel": {},
      "frequency": [2665],
      "location": ["CARTERTON EXCHANGE"],
      "gridRefDefault": ["LAT_LONG_NZGD2000_D2000"],
      "gridReference": ["-41.0252215 175.5278308"],
      "licenceType": ["Other (Spectrum)"],
      "status": ["Current"],
      "txrx": ["TX"],
      "suppressed": [false]
    },
    {
      "licenceID": [220332],
      "licenceNumber": [280799],
      "licensee": ["SPARK NEW ZEALAND TRADING LIMITED"],
      "channel": {},
      "frequency": [2665],
      "location": ["WEST END P A"],
      "gridRefDefault": ["LAT_LONG_NZGD2000_D2000"],
      "gridReference": ["-40.2816736 175.4512197"],
      "licenceType": ["Other (Spectrum)"],
      "status": ["Current"],
      "txrx": ["RX"],
      "suppressed": [false]
    },
    {
      "licenceID": [220332],
      "licenceNumber": [280799],
      "licensee": ["SPARK NEW ZEALAND TRADING LIMITED"],
      "channel": {},
      "frequency": [2665],
      "location": ["WEST END"],
      "gridRefDefault": ["LAT_LONG_NZGD2000_D2000"],
      "gridReference": ["-40.3685058 175.5725665"],
      "licenceType": ["Other (Spectrum)"],
      "status": ["Current"],
      "txrx": ["TX"],
      "suppressed": [false]
    },
    {
      "licenceID": [220331],
      "licenceNumber": [280800],
      "licensee": ["SPARK NEW ZEALAND TRADING LIMITED"],
      "channel": {},
      "frequency": [2665],
      "location": ["WAIUKU P A"],
      "gridRefDefault": ["LAT_LONG_NZGD2000_D2000"],
      "gridReference": ["-37.1655209 174.6537825"],
      "licenceType": ["Other (Spectrum)"],
      "status": ["Current"],
      "txrx": ["RX"],
      "suppressed": [false]
    },
    {
      "licenceID": [220331],
      "licenceNumber": [280800],
      "licensee": ["SPARK NEW ZEALAND TRADING LIMITED"],
      "channel": {},
      "frequency": [2665],
      "location": ["WAIUKU"],
      "gridRefDefault": ["LAT_LONG_NZGD2000_D2000"],
      "gridReference": ["-37.2529292 174.7696984"],
      "licenceType": ["Other (Spectrum)"],
      "status": ["Current"],
      "txrx": ["TX"],
      "suppressed": [false]
    },
    {
      "licenceID": [220330],
      "licenceNumber": [281080],
      "licensee": ["SPARK NEW ZEALAND TRADING LIMITED"],
      "channel": {},
      "frequency": [2665],
      "location": ["WATTLE DOWNS P A"],
      "gridRefDefault": ["LAT_LONG_NZGD2000_D2000"],
      "gridReference": ["-36.9546055 174.7677512"],
      "licenceType": ["Other (Spectrum)"],
      "status": ["Current"],
      "txrx": ["RX"],
      "suppressed": [false]
    },
    {
      "licenceID": [220330],
      "licenceNumber": [281080],
      "licensee": ["SPARK NEW ZEALAND TRADING LIMITED"],
      "channel": {},
      "frequency": [2665],
      "location": ["WATTLE DOWNS"],
      "gridRefDefault": ["LAT_LONG_NZGD2000_D2000"],
      "gridReference": ["-37.0420824 174.8829101"],
      "licenceType": ["Other (Spectrum)"],
      "status": ["Current"],
      "txrx": ["TX"],
      "suppressed": [false]
    },
    {
      "licenceID": [220329],
      "licenceNumber": [280963],
      "licensee": ["SPARK NEW ZEALAND TRADING LIMITED"],
      "channel": {},
      "frequency": [2665],
      "location": ["WESLEY P A"],
      "gridRefDefault": ["LAT_LONG_NZGD2000_D2000"],
      "gridReference": ["-36.8164570 174.6128912"],
      "licenceType": ["Other (Spectrum)"],
      "status": ["Current"],
      "txrx": ["RX"],
      "suppressed": [false]
    },
    {
      "licenceID": [220329],
      "licenceNumber": [280963],
      "licensee": ["SPARK NEW ZEALAND TRADING LIMITED"],
      "channel": {},
      "frequency": [2665],
      "location": ["WESLEY"],
      "gridRefDefault": ["LAT_LONG_NZGD2000_D2000"],
      "gridReference": ["-36.9047491 174.7271965"],
      "licenceType": ["Other (Spectrum)"],
      "status": ["Current"],
      "txrx": ["TX"],
      "suppressed": [false]
    },
    {
      "licenceID": [220328],
      "licenceNumber": [281100],
      "licensee": ["SPARK NEW ZEALAND TRADING LIMITED"],
      "channel": {},
      "frequency": [2665],
      "location": ["WESTERN SPRINGS P A"],
      "gridRefDefault": ["LAT_LONG_NZGD2000_D2000"],
      "gridReference": ["-36.7804020 174.6131643"],
      "licenceType": ["Other (Spectrum)"],
      "status": ["Current"],
      "txrx": ["RX"],
      "suppressed": [false]
    },
    {
      "licenceID": [220328],
      "licenceNumber": [281100],
      "licensee": ["SPARK NEW ZEALAND TRADING LIMITED"],
      "channel": {},
      "frequency": [2665],
      "location": ["WESTERN SPRINGS"],
      "gridRefDefault": ["LAT_LONG_NZGD2000_D2000"],
      "gridReference": ["-36.8684398 174.7280718"],
      "licenceType": ["Other (Spectrum)"],
      "status": ["Current"],
      "txrx": ["TX"],
      "suppressed": [false]
    },
    {
      "licenceID": [220327],
      "licenceNumber": [280826],
      "licensee": ["SPARK NEW ZEALAND TRADING LIMITED"],
      "channel": {},
      "frequency": [2665],
      "location": ["WHANGAPAROA RADIO STATION P A"],
      "gridRefDefault": ["LAT_LONG_NZGD2000_D2000"],
      "gridReference": ["-36.5380627 174.6063657"],
      "licenceType": ["Other (Spectrum)"],
      "status": ["Current"],
      "txrx": ["RX"],
      "suppressed": [false]
    },
    {
      "licenceID": [220327],
      "licenceNumber": [280826],
      "licensee": ["SPARK NEW ZEALAND TRADING LIMITED"],
      "channel": {},
      "frequency": [2665],
      "location": ["WHANGAPAROA RADIO STATION"],
      "gridRefDefault": ["LAT_LONG_NZGD2000_D2000"],
      "gridReference": ["-36.6258079 174.7203705"],
      "licenceType": ["Other (Spectrum)"],
      "status": ["Current"],
      "txrx": ["TX"],
      "suppressed": [false]
    },
    {
      "licenceID": [220326],
      "licenceNumber": [280949],
      "licensee": ["SPARK NEW ZEALAND TRADING LIMITED"],
      "channel": {},
      "frequency": [2665],
      "location": ["WOODLANDS PARK PA"],
      "gridRefDefault": ["LAT_LONG_NZGD2000_D2000"],
      "gridReference": ["-36.8647977 174.5091986"],
      "licenceType": ["Other (Spectrum)"],
      "status": ["Current"],
      "txrx": ["RX"],
      "suppressed": [false]
    },
    {
      "licenceID": [220326],
      "licenceNumber": [280949],
      "licensee": ["SPARK NEW ZEALAND TRADING LIMITED"],
      "channel": {},
      "frequency": [2665],
      "location": ["WOODLANDS PARK"],
      "gridRefDefault": ["LAT_LONG_NZGD2000_D2000"],
      "gridReference": ["-36.9532816 174.6239167"],
      "licenceType": ["Other (Spectrum)"],
      "status": ["Current"],
      "txrx": ["TX"],
      "suppressed": [false]
    },
    {
      "licenceID": [220325],
      "licenceNumber": [280767],
      "licensee": ["SPARK NEW ZEALAND TRADING LIMITED"],
      "channel": {},
      "frequency": [2665],
      "location": ["WAIMAUKU P A"],
      "gridRefDefault": ["LAT_LONG_NZGD2000_D2000"],
      "gridReference": ["-36.6890692 174.3816133"],
      "licenceType": ["Other (Spectrum)"],
      "status": ["Current"],
      "txrx": ["RX"],
      "suppressed": [false]
    },
    {
      "licenceID": [220325],
      "licenceNumber": [280767],
      "licensee": ["SPARK NEW ZEALAND TRADING LIMITED"],
      "channel": {},
      "frequency": [2665],
      "location": ["WAIMAUKU"],
      "gridRefDefault": ["LAT_LONG_NZGD2000_D2000"],
      "gridReference": ["-36.7774529 174.4956804"],
      "licenceType": ["Other (Spectrum)"],
      "status": ["Current"],
      "txrx": ["TX"],
      "suppressed": [false]
    },
    {
      "licenceID": [220324],
      "licenceNumber": [280991],
      "licensee": ["SPARK NEW ZEALAND TRADING LIMITED"],
      "channel": {},
      "frequency": [2665],
      "location": ["WESTMERE P A"],
      "gridRefDefault": ["LAT_LONG_NZGD2000_D2000"],
      "gridReference": ["-36.7661397 174.6027470"],
      "licenceType": ["Other (Spectrum)"],
      "status": ["Current"],
      "txrx": ["RX"],
      "suppressed": [false]
    },
    {
      "licenceID": [220324],
      "licenceNumber": [280991],
      "licensee": ["SPARK NEW ZEALAND TRADING LIMITED"],
      "channel": {},
      "frequency": [2665],
      "location": ["WESTMERE"],
      "gridRefDefault": ["LAT_LONG_NZGD2000_D2000"],
      "gridReference": ["-36.8543266 174.7179386"],
      "licenceType": ["Other (Spectrum)"],
      "status": ["Current"],
      "txrx": ["TX"],
      "suppressed": [false]
    },
    {
      "licenceID": [220323],
      "licenceNumber": [280933],
      "licensee": ["SPARK NEW ZEALAND TRADING LIMITED"],
      "channel": {},
      "frequency": [2665],
      "location": ["WAIAKE P A"],
      "gridRefDefault": ["LAT_LONG_NZGD2000_D2000"],
      "gridReference": ["-36.6196729 174.6328722"],
      "licenceType": ["Other (Spectrum)"],
      "status": ["Current"],
      "txrx": ["RX"],
      "suppressed": [false]
    },
    {
      "licenceID": [220323],
      "licenceNumber": [280933],
      "licensee": ["SPARK NEW ZEALAND TRADING LIMITED"],
      "channel": {},
      "frequency": [2665],
      "location": ["WAIAKE"],
      "gridRefDefault": ["LAT_LONG_NZGD2000_D2000"],
      "gridReference": ["-36.7076303 174.7479524"],
      "licenceType": ["Other (Spectrum)"],
      "status": ["Current"],
      "txrx": ["TX"],
      "suppressed": [false]
    },
    {
      "licenceID": [220322],
      "licenceNumber": [280757],
      "licensee": ["SPARK NEW ZEALAND TRADING LIMITED"],
      "channel": {},
      "frequency": [2665],
      "location": ["WAIUKU TOWN PA"],
      "gridRefDefault": ["LAT_LONG_NZGD2000_D2000"],
      "gridReference": ["-37.1618196 174.6128503"],
      "licenceType": ["Other (Spectrum)"],
      "status": ["Current"],
      "txrx": ["RX"],
      "suppressed": [false]
    },
    {
      "licenceID": [220322],
      "licenceNumber": [280757],
      "licensee": ["SPARK NEW ZEALAND TRADING LIMITED"],
      "channel": {},
      "frequency": [2665],
      "location": ["WAIUKU TOWN"],
      "gridRefDefault": ["LAT_LONG_NZGD2000_D2000"],
      "gridReference": ["-37.2502053 174.7281383"],
      "licenceType": ["Other (Spectrum)"],
      "status": ["Current"],
      "txrx": ["TX"],
      "suppressed": [false]
    },
    {
      "licenceID": [220321],
      "licenceNumber": [280835],
      "licensee": ["SPARK NEW ZEALAND TRADING LIMITED"],
      "channel": {},
      "frequency": [2665],
      "location": ["WILLIAMSON AVE P A"],
      "gridRefDefault": ["LAT_LONG_NZGD2000_D2000"],
      "gridReference": ["-36.7710842 174.6331106"],
      "licenceType": ["Other (Spectrum)"],
      "status": ["Current"],
      "txrx": ["RX"],
      "suppressed": [false]
    },
    {
      "licenceID": [220321],
      "licenceNumber": [280835],
      "licensee": ["SPARK NEW ZEALAND TRADING LIMITED"],
      "channel": {},
      "frequency": [2665],
      "location": ["WILLIAMSON AVE"],
      "gridRefDefault": ["LAT_LONG_NZGD2000_D2000"],
      "gridReference": ["-36.8593876 174.7476869"],
      "licenceType": ["Other (Spectrum)"],
      "status": ["Current"],
      "txrx": ["TX"],
      "suppressed": [false]
    },
    {
      "licenceID": [220320],
      "licenceNumber": [281050],
      "licensee": ["SPARK NEW ZEALAND TRADING LIMITED"],
      "channel": {},
      "frequency": [2665],
      "location": ["WHENUAPAI P A"],
      "gridRefDefault": ["LAT_LONG_NZGD2000_D2000"],
      "gridReference": ["-36.7036207 174.5027896"],
      "licenceType": ["Other (Spectrum)"],
      "status": ["Current"],
      "txrx": ["RX"],
      "suppressed": [false]
    },
    {
      "licenceID": [220320],
      "licenceNumber": [281050],
      "licensee": ["SPARK NEW ZEALAND TRADING LIMITED"],
      "channel": {},
      "frequency": [2665],
      "location": ["WHENUAPAI"],
      "gridRefDefault": ["LAT_LONG_NZGD2000_D2000"],
      "gridReference": ["-36.7917548 174.6169274"],
      "licenceType": ["Other (Spectrum)"],
      "status": ["Current"],
      "txrx": ["TX"],
      "suppressed": [false]
    },
    {
      "licenceID": [220319],
      "licenceNumber": [280994],
      "licensee": ["SPARK NEW ZEALAND TRADING LIMITED"],
      "channel": {},
      "frequency": [2665],
      "location": ["WEST HARBOUR P A"],
      "gridRefDefault": ["LAT_LONG_NZGD2000_D2000"],
      "gridReference": ["-36.7221539 174.5300676"],
      "licenceType": ["Other (Spectrum)"],
      "status": ["Current"],
      "txrx": ["RX"],
      "suppressed": [false]
    },
    {
      "licenceID": [220319],
      "licenceNumber": [280994],
      "licensee": ["SPARK NEW ZEALAND TRADING LIMITED"],
      "channel": {},
      "frequency": [2665],
      "location": ["WEST HARBOUR"],
      "gridRefDefault": ["LAT_LONG_NZGD2000_D2000"],
      "gridReference": ["-36.8103574 174.6450851"],
      "licenceType": ["Other (Spectrum)"],
      "status": ["Current"],
      "txrx": ["TX"],
      "suppressed": [false]
    },
    {
      "licenceID": [220318],
      "licenceNumber": [280986],
      "licensee": ["SPARK NEW ZEALAND TRADING LIMITED"],
      "channel": {},
      "frequency": [2665],
      "location": ["WOODBAY P A"],
      "gridRefDefault": ["LAT_LONG_NZGD2000_D2000"],
      "gridReference": ["-36.8497294 174.5576017"],
      "licenceType": ["Other (Spectrum)"],
      "status": ["Current"],
      "txrx": ["RX"],
      "suppressed": [false]
    },
    {
      "licenceID": [220318],
      "licenceNumber": [280986],
      "licensee": ["SPARK NEW ZEALAND TRADING LIMITED"],
      "channel": {},
      "frequency": [2665],
      "location": ["WOODBAY"],
      "gridRefDefault": ["LAT_LONG_NZGD2000_D2000"],
      "gridReference": ["-36.9373903 174.6724364"],
      "licenceType": ["Other (Spectrum)"],
      "status": ["Current"],
      "txrx": ["TX"],
      "suppressed": [false]
    },
    {
      "licenceID": [220317],
      "licenceNumber": [280899],
      "licensee": ["SPARK NEW ZEALAND TRADING LIMITED"],
      "channel": {},
      "frequency": [2665],
      "location": ["VICTORIA SQUARE PA"],
      "gridRefDefault": ["LAT_LONG_NZGD2000_D2000"],
      "gridReference": ["-36.7592164 174.6429097"],
      "licenceType": ["Other (Spectrum)"],
      "status": ["Current"],
      "txrx": ["RX"],
      "suppressed": [false]
    },
    {
      "licenceID": [220317],
      "licenceNumber": [280899],
      "licensee": ["SPARK NEW ZEALAND TRADING LIMITED"],
      "channel": {},
      "frequency": [2665],
      "location": ["VICTORIA SQUARE"],
      "gridRefDefault": ["LAT_LONG_NZGD2000_D2000"],
      "gridReference": ["-36.8475069 174.7576927"],
      "licenceType": ["Other (Spectrum)"],
      "status": ["Current"],
      "txrx": ["TX"],
      "suppressed": [false]
    },
    {
      "licenceID": [220316],
      "licenceNumber": [280846],
      "licensee": ["SPARK NEW ZEALAND TRADING LIMITED"],
      "channel": {},
      "frequency": [2665],
      "location": ["VALLEY ROAD P A"],
      "gridRefDefault": ["LAT_LONG_NZGD2000_D2000"],
      "gridReference": ["-36.7881677 174.6357578"],
      "licenceType": ["Other (Spectrum)"],
      "status": ["Current"],
      "txrx": ["RX"],
      "suppressed": [false]
    },
    {
      "licenceID": [220316],
      "licenceNumber": [280846],
      "licensee": ["SPARK NEW ZEALAND TRADING LIMITED"],
      "channel": {},
      "frequency": [2665],
      "location": ["VALLEY ROAD"],
      "gridRefDefault": ["LAT_LONG_NZGD2000_D2000"],
      "gridReference": ["-36.8769756 174.7502297"],
      "licenceType": ["Other (Spectrum)"],
      "status": ["Current"],
      "txrx": ["TX"],
      "suppressed": [false]
    },
    {
      "licenceID": [220315],
      "licenceNumber": [281107],
      "licensee": ["SPARK NEW ZEALAND TRADING LIMITED"],
      "channel": {},
      "frequency": [2665],
      "location": ["VICTORIA PARK PA"],
      "gridRefDefault": ["LAT_LONG_NZGD2000_D2000"],
      "gridReference": ["-36.7541940 174.6389703"],
      "licenceType": ["Other (Spectrum)"],
      "status": ["Current"],
      "txrx": ["RX"],
      "suppressed": [false]
    },
    {
      "licenceID": [220315],
      "licenceNumber": [281107],
      "licensee": ["SPARK NEW ZEALAND TRADING LIMITED"],
      "channel": {},
      "frequency": [2665],
      "location": ["VICTORIA PARK"],
      "gridRefDefault": ["LAT_LONG_NZGD2000_D2000"],
      "gridReference": ["-36.8425525 174.7536755"],
      "licenceType": ["Other (Spectrum)"],
      "status": ["Current"],
      "txrx": ["TX"],
      "suppressed": [false]
    },
    {
      "licenceID": [220314],
      "licenceNumber": [280814],
      "licensee": ["SPARK NEW ZEALAND TRADING LIMITED"],
      "channel": {},
      "frequency": [2665],
      "location": ["UPPER HARBOUR DRIVE P A"],
      "gridRefDefault": ["LAT_LONG_NZGD2000_D2000"],
      "gridReference": ["-36.6871420 174.5818784"],
      "licenceType": ["Other (Spectrum)"],
      "status": ["Current"],
      "txrx": ["RX"],
      "suppressed": [false]
    },
    {
      "licenceID": [220314],
      "licenceNumber": [280814],
      "licensee": ["SPARK NEW ZEALAND TRADING LIMITED"],
      "channel": {},
      "frequency": [2665],
      "location": ["UPPER HARBOUR DRIVE"],
      "gridRefDefault": ["LAT_LONG_NZGD2000_D2000"],
      "gridReference": ["-36.7746896 174.6964407"],
      "licenceType": ["Other (Spectrum)"],
      "status": ["Current"],
      "txrx": ["TX"],
      "suppressed": [false]
    },
    {
      "licenceID": [220313],
      "licenceNumber": [281005],
      "licensee": ["SPARK NEW ZEALAND TRADING LIMITED"],
      "channel": {},
      "frequency": [2665],
      "location": ["TE ATATU SOUTH RELOCATION P A"],
      "gridRefDefault": ["LAT_LONG_NZGD2000_D2000"],
      "gridReference": ["-36.7987680 174.5295447"],
      "licenceType": ["Other (Spectrum)"],
      "status": ["Current"],
      "txrx": ["RX"],
      "suppressed": [false]
    },
    {
      "licenceID": [220313],
      "licenceNumber": [281005],
      "licensee": ["SPARK NEW ZEALAND TRADING LIMITED"],
      "channel": {},
      "frequency": [2665],
      "location": ["TE ATATU SOUTH RELOCATION"],
      "gridRefDefault": ["LAT_LONG_NZGD2000_D2000"],
      "gridReference": ["-36.8868216 174.6445040"],
      "licenceType": ["Other (Spectrum)"],
      "status": ["Current"],
      "txrx": ["TX"],
      "suppressed": [false]
    },
    {
      "licenceID": [220312],
      "licenceNumber": [280795],
      "licensee": ["SPARK NEW ZEALAND TRADING LIMITED"],
      "channel": {},
      "frequency": [2665],
      "location": ["TUAKAU P A"],
      "gridRefDefault": ["LAT_LONG_NZGD2000_D2000"],
      "gridReference": ["-37.1763637 174.8196156"],
      "licenceType": ["Other (Spectrum)"],
      "status": ["Current"],
      "txrx": ["RX"],
      "suppressed": [false]
    },
    {
      "licenceID": [220312],
      "licenceNumber": [280795],
      "licensee": ["SPARK NEW ZEALAND TRADING LIMITED"],
      "channel": {},
      "frequency": [2665],
      "location": ["TUAKAU"],
      "gridRefDefault": ["LAT_LONG_NZGD2000_D2000"],
      "gridReference": ["-37.2644632 174.9348755"],
      "licenceType": ["Other (Spectrum)"],
      "status": ["Current"],
      "txrx": ["TX"],
      "suppressed": [false]
    },
    {
      "licenceID": [220311],
      "licenceNumber": [280972],
      "licensee": ["SPARK NEW ZEALAND TRADING LIMITED"],
      "channel": {},
      "frequency": [2665],
      "location": ["TUI BRAE P A"],
      "gridRefDefault": ["LAT_LONG_NZGD2000_D2000"],
      "gridReference": ["-36.8031521 174.8759678"],
      "licenceType": ["Other (Spectrum)"],
      "status": ["Current"],
      "txrx": ["RX"],
      "suppressed": [false]
    },
    {
      "licenceID": [220311],
      "licenceNumber": [280972],
      "licensee": ["SPARK NEW ZEALAND TRADING LIMITED"],
      "channel": {},
      "frequency": [2665],
      "location": ["TUI BRAE"],
      "gridRefDefault": ["LAT_LONG_NZGD2000_D2000"],
      "gridReference": ["-36.8908550 174.9906174"],
      "licenceType": ["Other (Spectrum)"],
      "status": ["Current"],
      "txrx": ["TX"],
      "suppressed": [false]
    },
    {
      "licenceID": [220310],
      "licenceNumber": [281092],
      "licensee": ["SPARK NEW ZEALAND TRADING LIMITED"],
      "channel": {},
      "frequency": [2665],
      "location": ["TITIRANGI NORTH P A"],
      "gridRefDefault": ["LAT_LONG_NZGD2000_D2000"],
      "gridReference": ["-36.8336931 174.5449032"],
      "licenceType": ["Other (Spectrum)"],
      "status": ["Current"],
      "txrx": ["RX"],
      "suppressed": [false]
    },
    {
      "licenceID": [220310],
      "licenceNumber": [281092],
      "licensee": ["SPARK NEW ZEALAND TRADING LIMITED"],
      "channel": {},
      "frequency": [2665],
      "location": ["TITIRANGI NORTH"],
      "gridRefDefault": ["LAT_LONG_NZGD2000_D2000"],
      "gridReference": ["-36.9212056 174.6595943"],
      "licenceType": ["Other (Spectrum)"],
      "status": ["Current"],
      "txrx": ["TX"],
      "suppressed": [false]
    },
    {
      "licenceID": [220309],
      "licenceNumber": [281030],
      "licensee": ["SPARK NEW ZEALAND TRADING LIMITED"],
      "channel": {},
      "frequency": [2665],
      "location": ["THREE KINGS SHOPPING CENTRE P A"],
      "gridRefDefault": ["LAT_LONG_NZGD2000_D2000"],
      "gridReference": ["-36.8214509 174.6399135"],
      "licenceType": ["Other (Spectrum)"],
      "status": ["Current"],
      "txrx": ["RX"],
      "suppressed": [false]
    },
    {
      "licenceID": [220309],
      "licenceNumber": [281030],
      "licensee": ["SPARK NEW ZEALAND TRADING LIMITED"],
      "channel": {},
      "frequency": [2665],
      "location": ["THREE KINGS SHOPPING CENTRE"],
      "gridRefDefault": ["LAT_LONG_NZGD2000_D2000"],
      "gridReference": ["-36.9093495 174.7546863"],
      "licenceType": ["Other (Spectrum)"],
      "status": ["Current"],
      "txrx": ["TX"],
      "suppressed": [false]
    },
    {
      "licenceID": [220308],
      "licenceNumber": [280869],
      "licensee": ["SPARK NEW ZEALAND TRADING LIMITED"],
      "channel": {},
      "frequency": [2665],
      "location": ["TAKANINI RELOCATION PA"],
      "gridRefDefault": ["LAT_LONG_NZGD2000_D2000"],
      "gridReference": ["-36.9504800 174.7990895"],
      "licenceType": ["Other (Spectrum)"],
      "status": ["Current"],
      "txrx": ["RX"],
      "suppressed": [false]
    },
    {
      "licenceID": [220308],
      "licenceNumber": [280869],
      "licensee": ["SPARK NEW ZEALAND TRADING LIMITED"],
      "channel": {},
      "frequency": [2665],
      "location": ["TAKANINI RELOCATION"],
      "gridRefDefault": ["LAT_LONG_NZGD2000_D2000"],
      "gridReference": ["-37.0378523 174.9148950"],
      "licenceType": ["Other (Spectrum)"],
      "status": ["Current"],
      "txrx": ["TX"],
      "suppressed": [false]
    },
    {
      "licenceID": [220307],
      "licenceNumber": [281062],
      "licensee": ["SPARK NEW ZEALAND TRADING LIMITED"],
      "channel": {},
      "frequency": [2665],
      "location": ["TAKAPUNA CITY P A"],
      "gridRefDefault": ["LAT_LONG_NZGD2000_D2000"],
      "gridReference": ["-36.7004112 174.6571752"],
      "licenceType": ["Other (Spectrum)"],
      "status": ["Current"],
      "txrx": ["RX"],
      "suppressed": [false]
    },
    {
      "licenceID": [220307],
      "licenceNumber": [281062],
      "licensee": ["SPARK NEW ZEALAND TRADING LIMITED"],
      "channel": {},
      "frequency": [2665],
      "location": ["TAKAPUNA CITY"],
      "gridRefDefault": ["LAT_LONG_NZGD2000_D2000"],
      "gridReference": ["-36.7883989 174.7713754"],
      "licenceType": ["Other (Spectrum)"],
      "status": ["Current"],
      "txrx": ["TX"],
      "suppressed": [false]
    },
    {
      "licenceID": [220306],
      "licenceNumber": [280830],
      "licensee": ["SPARK NEW ZEALAND TRADING LIMITED"],
      "channel": {},
      "frequency": [2665],
      "location": ["TORBAY P A"],
      "gridRefDefault": ["LAT_LONG_NZGD2000_D2000"],
      "gridReference": ["-36.6119240 174.6092110"],
      "licenceType": ["Other (Spectrum)"],
      "status": ["Current"],
      "txrx": ["RX"],
      "suppressed": [false]
    },
    {
      "licenceID": [220306],
      "licenceNumber": [280830],
      "licensee": ["SPARK NEW ZEALAND TRADING LIMITED"],
      "channel": {},
      "frequency": [2665],
      "location": ["TORBAY"],
      "gridRefDefault": ["LAT_LONG_NZGD2000_D2000"],
      "gridReference": ["-36.6999283 174.7233239"],
      "licenceType": ["Other (Spectrum)"],
      "status": ["Current"],
      "txrx": ["TX"],
      "suppressed": [false]
    },
    {
      "licenceID": [220305],
      "licenceNumber": [281008],
      "licensee": ["SPARK NEW ZEALAND TRADING LIMITED"],
      "channel": {},
      "frequency": [2665],
      "location": ["TE ATATU NORTH P A"],
      "gridRefDefault": ["LAT_LONG_NZGD2000_D2000"],
      "gridReference": ["-36.7428435 174.5327711"],
      "licenceType": ["Other (Spectrum)"],
      "status": ["Current"],
      "txrx": ["RX"],
      "suppressed": [false]
    },
    {
      "licenceID": [220305],
      "licenceNumber": [281008],
      "licensee": ["SPARK NEW ZEALAND TRADING LIMITED"],
      "channel": {},
      "frequency": [2665],
      "location": ["TE ATATU NORTH"],
      "gridRefDefault": ["LAT_LONG_NZGD2000_D2000"],
      "gridReference": ["-36.8304824 174.6474503"],
      "licenceType": ["Other (Spectrum)"],
      "status": ["Current"],
      "txrx": ["TX"],
      "suppressed": [false]
    },
    {
      "licenceID": [220304],
      "licenceNumber": [281013],
      "licensee": ["SPARK NEW ZEALAND TRADING LIMITED"],
      "channel": {},
      "frequency": [2665],
      "location": ["SYMONDS STREET P A"],
      "gridRefDefault": ["LAT_LONG_NZGD2000_D2000"],
      "gridReference": ["-36.7680870 174.6520838"],
      "licenceType": ["Other (Spectrum)"],
      "status": ["Current"],
      "txrx": ["RX"],
      "suppressed": [false]
    },
    {
      "licenceID": [220304],
      "licenceNumber": [281013],
      "licensee": ["SPARK NEW ZEALAND TRADING LIMITED"],
      "channel": {},
      "frequency": [2665],
      "location": ["SYMONDS STREET"],
      "gridRefDefault": ["LAT_LONG_NZGD2000_D2000"],
      "gridReference": ["-36.8560770 174.7665356"],
      "licenceType": ["Other (Spectrum)"],
      "status": ["Current"],
      "txrx": ["TX"],
      "suppressed": [false]
    },
    {
      "licenceID": [220303],
      "licenceNumber": [281088],
      "licensee": ["SPARK NEW ZEALAND TRADING LIMITED"],
      "channel": {},
      "frequency": [2665],
      "location": ["SWANSON P A"],
      "gridRefDefault": ["LAT_LONG_NZGD2000_D2000"],
      "gridReference": ["-36.7770269 174.4741607"],
      "licenceType": ["Other (Spectrum)"],
      "status": ["Current"],
      "txrx": ["RX"],
      "suppressed": [false]
    },
    {
      "licenceID": [220303],
      "licenceNumber": [281088],
      "licensee": ["SPARK NEW ZEALAND TRADING LIMITED"],
      "channel": {},
      "frequency": [2665],
      "location": ["SWANSON"],
      "gridRefDefault": ["LAT_LONG_NZGD2000_D2000"],
      "gridReference": ["-36.8654565 174.5885480"],
      "licenceType": ["Other (Spectrum)"],
      "status": ["Current"],
      "txrx": ["TX"],
      "suppressed": [false]
    }
  ],
  "links": []
}
